Workbook
Name Slicer_Employee_Name: #N/A
Name Slicer_Employee_Name1: #N/A

Sheet Brokerage 
A1: client_name | B1: policy_number | C1: policy_status | D1: policy_start_date | E1: policy_end_date | F1: product_group | G1: Account Executive | H1: branch_name | I1: solution_group | J1: income_class | K1: Amount | L1: income_due_date | M1: revenue_transaction_type | N1: renewal_status | O1: lapse_reason | P1: last_updated_date
A2: A | B2: 2414 2022 4088 1000 000 | C2: Active | D2: 43209 | E2: 43573 | F2: Marine | G2: Vinay | H2: Ahmedabad | I2: Marine | J2: Renewal | K2: 32186.72 | L2: 43209 | M2: Brokerage | N2: Inception | P2: 43852
A3: Amit | B3: 2.4142028e+18 | C3: Active | D3: 43586 | E3: 43951 | F3: Marine | G3: Abhinav Shivam | H3: Ahmedabad | I3: Marine | J3: New | K3: 23590.71 | L3: 43586 | M3: Brokerage | N3: Inception | P3: 43852
A4: B | B4: 0655001825 01 | C4: Inactive | D4: 43356 | E4: 43720 | F4: Fire | G4: Vinay | H4: Ahmedabad | I4: Construction, Power & Infrastructure | J4: Renewal | K4: 4611.96 | L4: 43356 | M4: Brokerage | N4: Inception | P4: 43852
A5: B | B5: 12139156 | C5: Active | D5: 43721 | E5: 44086 | F5: Fire | G5: Vinay | H5: Ahmedabad | I5: Construction, Power & Infrastructure | J5: Renewal | K5: 4975.41 | L5: 43721 | M5: Brokerage | N5: Renewal | P5: 43852
A6: B | B6: 2200090892 | C6: Active | D6: 43410 | E6: 43774 | F6: Miscellaneous | G6: Vinay | H6: Ahmedabad | I6: Liability | J6: Renewal | K6: 1198.88 | L6: 43410 | M6: Brokerage | N6: Inception | P6: 43852
A7: C | B7: 237164239 00 | C7: Active | D7: 43497 | E7: 43861 | F7: Employee Benefits | G7: Mark | H7: Ahmedabad | I7: Employee Benefits (EB) | J7: Renewal | K7: 1825.43 | L7: 43497 | M7: Brokerage | N7: Inception | P7: 43852
A8: D | B8: 4101190700000015-00 | C8: Active | D8: 43641 | E8: 44006 | F8: Employee Benefits | G8: Abhinav Shivam | H8: Ahmedabad | I8: Employee Benefits (EB) | J8: New | K8: 79833.6 | L8: 43641 | M8: Brokerage | N8: Endorsement | P8: 43852
A9: D | B9: 4101190700000015-00 | C9: Active | D9: 43641 | E9: 44006 | F9: Employee Benefits | G9: Abhinav Shivam | H9: Ahmedabad | I9: Employee Benefits (EB) | J9: New | K9: 11435.86 | L9: 43679 | M9: Brokerage | N9: Endorsement | P9: 43852
A10: E | B10: 2250010276 | C10: Active | D10: 43215 | E10: 43579 | F10: Miscellaneous | G10: Vinay | H10: Ahmedabad | I10: Employee Benefits (EB) | J10: Renewal | K10: 847.38 | L10: 43215 | M10: Brokerage | N10: Inception | P10: 43852
A11: E | B11: 2414 2022 1261 2200 000 | C11: Inactive | D11: 43215 | E11: 43579 | F11: Marine | G11: Vinay | H11: Ahmedabad | I11: Marine | J11: Renewal | K11: 9900 | L11: 43215 | M11: Brokerage | N11: Inception | P11: 43852
A12: E | B12: 2414 2026 2374 7800 000 | C12: Active | D12: 43476 | E12: 43840 | F12: Marine | G12: Vinay | H12: Ahmedabad | I12: Marine | J12: Renewal | K12: 8250 | L12: 43476 | M12: Brokerage | N12: Renewal | P12: 43852
A13: E | B13: 91001900000001 | C13: Active | D13: 43215 | E13: 43579 | F13: Fire | G13: Vinay | H13: Ahmedabad | I13: Property / BI | J13: Renewal | K13: 4093.2 | L13: 43215 | M13: Brokerage | N13: Inception | P13: 43852
A14: F | B14: 2280062933 | C14: Active | D14: 43605 | E14: 43970 | F14: Miscellaneous | G14: Vinay | H14: Ahmedabad | I14: Liability | J14: Renewal | K14: 8117 | L14: 43850 | M14: Brokerage | N14: Renewal | P14: 43852
A15: F | B15: LWC/I2568913/71/05/006144 | C15: Inactive | D15: 43240 | E15: 43604 | F15: Miscellaneous | G15: Vinay | H15: Ahmedabad | I15: Liability | J15: Renewal | K15: 6101.25 | L15: 43240 | M15: Brokerage | N15: Inception | P15: 43852
A16: G | B16: 0865074115 01 | C16: Active | D16: 43263 | E16: 43627 | F16: Marine | G16: Manish Sharma | H16: Ahmedabad | I16: Small Medium Enterpries (SME) | J16: Renewal | K16: 1980 | L16: 43263 | M16: Brokerage | N16: Endorsement | P16: 43852
A17: G | B17: 0865074115 01 | C17: Active | D17: 43263 | E17: 43627 | F17: Marine | G17: Manish Sharma | H17: Ahmedabad | I17: Small Medium Enterpries (SME) | J17: Renewal | K17: 1980 | L17: 43475 | M17: Brokerage | N17: Endorsement | P17: 43852
A18: H | B18: 3.114203e+18 | C18: Active | D18: 43703 | E18: 44068 | F18: Miscellaneous | G18: Animesh Rawat | H18: Ahmedabad | I18: Global Client Network (GNB Inward) | J18: Cross Sell | K18: 2089.25 | L18: 43703 | M18: Brokerage | N18: Inception | P18: 43852
A19: H | B19: OG-19-2202-1018-00000055 | C19: Active | D19: 43466 | E19: 43830 | F19: Marine | G19: Animesh Rawat | H19: Ahmedabad | I19: Global Client Network (GNB Inward) | J19: Cross Sell | K19: 21768.61 | L19: 43466 | M19: Brokerage | N19: Inception | P19: 43852
A20: H | B20: OG-19-2202-3383-00000009 | C20: Active | D20: 43466 | E20: 43830 | F20: Liability | G20: Animesh Rawat | H20: Ahmedabad | I20: Global Client Network (GNB Inward) | J20: Cross Sell | K20: 12019.2 | L20: 43466 | M20: Brokerage | N20: Inception | P20: 43852
A21: I | B21: 640002371 | C21: Active | D21: 43191 | E21: 43555 | F21: Miscellaneous | G21: Animesh Rawat | H21: Ahmedabad | I21: Global Client Network (GNB Inward) | J21: Renewal | K21: 66937.72 | L21: 43191 | M21: Brokerage | N21: Inception | P21: 43852
A22: I | B22: 0830017443 01 | C22: Active | D22: 43231 | E22: 43595 | F22: Marine | G22: Animesh Rawat | H22: Ahmedabad | I22: Global Client Network (GNB Inward) | J22: Renewal | K22: 78374.84 | L22: 43231 | M22: Brokerage | N22: Inception | P22: 43852
A23: I | B23: 180876-0000-00 | C23: Inactive | D23: 43191 | E23: 43555 | F23: Employee Benefits | G23: Mark | H23: Ahmedabad | I23: Employee Benefits (EB) | J23: Renewal | K23: 60000 | L23: 43191 | M23: Brokerage | N23: Inception | P23: 43852
A24: I | B24: 180876-0000-01 | C24: Active | D24: 43556 | E24: 43921 | F24: Employee Benefits | G24: Mark | H24: Ahmedabad | I24: Employee Benefits (EB) | J24: Renewal | K24: 60000 | L24: 43556 | M24: Brokerage | N24: Renewal | P24: 43852
A25: I | B25: 180876-0000-01 | C25: Active | D25: 43556 | E25: 43921 | F25: Employee Benefits | G25: Mark | H25: Ahmedabad | I25: Employee Benefits (EB) | J25: Renewal | K25: 60000 | L25: 43556 | M25: Brokerage | N25: Renewal | P25: 43852
A26: I | B26: 2250002346 | C26: Active | D26: 43191 | E26: 43555 | F26: Miscellaneous | G26: Animesh Rawat | H26: Ahmedabad | I26: Global Client Network (GNB Inward) | J26: Renewal | K26: 4715.63 | L26: 43191 | M26: Brokerage | N26: Inception | P26: 43852
A27: I | B27: 3.1242014e+18 | C27: Active | D27: 43191 | E27: 43555 | F27: Liability | G27: Animesh Rawat | H27: Ahmedabad | I27: Global Client Network (GNB Inward) | J27: Renewal | K27: 22755.25 | L27: 43191 | M27: Brokerage | N27: Inception | P27: 43852
A28: I | B28: P0119200001/9999/100017 | C28: Active | D28: 43191 | E28: 43555 | F28: Liability | G28: Shivani Sharma | H28: Ahmedabad | I28: Global Client Network (GNB Inward) | J28: Renewal | K28: 26443.63 | L28: 43191 | M28: Brokerage | N28: Inception | P28: 43852
A29: J | B29: 0865078325 00 | C29: Inactive | D29: 43196 | E29: 43560 | F29: Marine | G29: Vinay | H29: Ahmedabad | I29: Marine | J29: Renewal | K29: 49499.84 | L29: 43196 | M29: Brokerage | N29: Endorsement | P29: 43852
A30: J | B30: 0865078325 00 | C30: Inactive | D30: 43196 | E30: 43560 | F30: Marine | G30: Vinay | H30: Ahmedabad | I30: Marine | J30: Renewal | L30: 43384 | M30: Brokerage | N30: Endorsement | P30: 43852
A31: J | B31: 0865078325 00 | C31: Inactive | D31: 43196 | E31: 43560 | F31: Marine | G31: Vinay | H31: Ahmedabad | I31: Marine | J31: Renewal | K31: 16500 | L31: 43482 | M31: Brokerage | N31: Endorsement | P31: 43852
A32: J | B32: '0865078325 01 | C32: Active | D32: 43561 | E32: 43926 | F32: Marine | G32: Vinay | H32: Ahmedabad | I32: Marine | J32: Renewal | K32: 26400 | L32: 43561 | M32: Brokerage | N32: Renewal | P32: 43852
A33: J | B33: 0865080591 00 | C33: Active | D33: 43332 | E33: 43696 | F33: Marine | G33: Vinay | H33: Ahmedabad | I33: Marine | J33: Renewal | K33: 3300 | L33: 43332 | M33: Brokerage | N33: Inception | P33: 43852
A34: J | B34: 0865081032 00 | C34: Active | D34: 43354 | E34: 43718 | F34: Marine | G34: Vinay | H34: Ahmedabad | I34: Marine | J34: Renewal | K34: 1072.5 | L34: 43354 | M34: Brokerage | N34: Inception | P34: 43852
A35: J | B35: '310304111710000871 | C35: Active | D35: 43186 | E35: 43550 | F35: Fire | G35: Vinay | H35: Ahmedabad | I35: Property / BI | J35: Renewal | K35: 4002.46 | L35: 43186 | M35: Brokerage | N35: Inception | P35: 43852
A36: J | B36: 3.1030411e+17 | C36: Active | D36: 43326 | E36: 43690 | F36: Fire | G36: Vinay | H36: Ahmedabad | I36: Property / BI | J36: Renewal | K36: 1374.25 | L36: 43326 | M36: Brokerage | N36: Inception | P36: 43852
A37: J | B37: 3.1030459e+18 | C37: Active | D37: 43186 | E37: 43550 | F37: Fire | G37: Vinay | H37: Ahmedabad | I37: Property / BI | J37: Cross Sell | K37: 566.25 | L37: 43186 | M37: Brokerage | N37: Inception | P37: 43852
A38: J | B38: '310304591810000063 | C38: Active | D38: 43326 | E38: 43690 | F38: Miscellaneous | G38: Vinay | H38: Ahmedabad | I38: Property / BI | J38: Renewal | K38: 445 | L38: 43326 | M38: Brokerage | N38: Inception | P38: 43852
A39: K | B39: '310300111910000401 | C39: Active | D39: 43709 | E39: 44074 | F39: Fire | G39: Vinay | H39: Ahmedabad | I39: Property / BI | J39: Renewal | K39: 13114.95 | L39: 43709 | M39: Brokerage | N39: Renewal | P39: 43852
A40: K | B40: 3.1030411e+17 | C40: Inactive | D40: 43344 | E40: 43708 | F40: Fire | G40: Vinay | H40: Ahmedabad | I40: Property / BI | J40: Renewal | K40: 2049.42 | L40: 43344 | M40: Brokerage | N40: Inception | P40: 43852
A41: L | B41: 301002850 | C41: Active | D41: 43313 | E41: 43677 | F41: Liability | G41: Ketan Jain | H41: Ahmedabad | I41: Liability | J41: Renewal | K41: 61425 | L41: 43313 | M41: Brokerage | N41: Inception | P41: 43852
A42: M | B42: 2.4122019e+18 | C42: Active | D42: 43370 | E42: 43734 | F42: Marine | G42: Vinay | H42: Ahmedabad | I42: Marine | J42: Renewal | K42: 1650 | L42: 43370 | M42: Brokerage | N42: Inception | P42: 43852
A43: N | B43: 0830018899Â 01 | C43: Inactive | D43: 43160 | E43: 43524 | F43: Marine | G43: Animesh Rawat | H43: Ahmedabad | I43: Global Client Network (GNB Inward) | J43: Renewal | K43: 16335 | L43: 43160 | M43: Brokerage | N43: Inception | P43: 43852
A44: N | B44: OG-19-2202-1018-00000059 | C44: Active | D44: 43525 | E44: 43890 | F44: Marine | G44: Animesh Rawat | H44: Ahmedabad | I44: Global Client Network (GNB Inward) | J44: Renewal | K44: 18562.5 | L44: 43525 | M44: Brokerage | N44: Renewal | P44: 43852
A45: O | B45: OG-19-2001-3315-00000015 | C45: Active | D45: 43192 | E45: 43556 | F45: Liability | G45: Shivani Sharma | H45: Ahmedabad | I45: Global Client Network (GNB Inward) | J45: Renewal | K45: 0 | L45: 43314 | M45: Brokerage | N45: Inception | P45: 43852
A46: P | B46: 4005/134645920/01/000 | C46: Inactive | D46: 43280 | E46: 43644 | F46: Employee Benefits | G46: Mark | H46: Ahmedabad | I46: Employee Benefits (EB) | J46: Renewal | K46: 4330.05 | L46: 43280 | M46: Brokerage | N46: Endorsement | P46: 43852
A47: P | B47: 4005/134645920/01/000 | C47: Inactive | D47: 43280 | E47: 43644 | F47: Employee Benefits | G47: Mark | H47: Ahmedabad | I47: Employee Benefits (EB) | J47: Renewal | L47: 43286 | M47: Brokerage | N47: Endorsement | P47: 43852
A48: P | B48: 4005/134645920/02/000 | C48: Active | D48: 43645 | E48: 44010 | F48: Employee Benefits | G48: Mark | H48: Ahmedabad | I48: Employee Benefits (EB) | J48: Renewal | K48: 8604.68 | L48: 43645 | M48: Brokerage | N48: Renewal | P48: 43852
A49: P | B49: 4016/133979727/01/000 | C49: Inactive | D49: 43280 | E49: 43644 | F49: Employee Benefits | G49: Mark | H49: Ahmedabad | I49: Employee Benefits (EB) | J49: Renewal | K49: 41313.6 | L49: 43280 | M49: Brokerage | N49: Endorsement | P49: 43852
A50: P | B50: 4016/133979727/01/000 | C50: Inactive | D50: 43280 | E50: 43644 | F50: Employee Benefits | G50: Mark | H50: Ahmedabad | I50: Employee Benefits (EB) | J50: Renewal | L50: 43312 | M50: Brokerage | N50: Endorsement | P50: 43852
A51: P | B51: 4016/133979727/02/000 | C51: Active | D51: 43645 | E51: 44010 | F51: Employee Benefits | G51: Mark | H51: Ahmedabad | I51: Employee Benefits (EB) | J51: Renewal | K51: 74672.78 | L51: 43645 | M51: Brokerage | N51: Renewal | P51: 43852
A52: O | B52: 0865078861 00 | C52: Active | D52: 43103 | E52: 43467 | F52: Marine | G52: Shivani Sharma | H52: Ahmedabad | I52: Global Client Network (GNB Inward) | J52: Renewal | K52: 66622.35 | L52: 43103 | M52: Brokerage | N52: Inception | P52: 43852
A53: O | B53: 4066/130374729/01/000 | C53: Active | D53: 43191 | E53: 43555 | F53: Liability | G53: Shivani Sharma | H53: Ahmedabad | I53: Global Client Network (GNB Inward) | J53: Renewal | K53: 0 | L53: 43191 | M53: Brokerage | N53: Inception | P53: 43852
A54: q | B54: 2002/160040691/00/000 | C54: Inactive | D54: 43405 | E54: 43769 | F54: Marine | G54: Vinay | H54: Ahmedabad | I54: Marine | J54: Renewal | K54: 92812.5 | L54: 43405 | M54: Brokerage | N54: Renewal | P54: 43852
A55: q | B55: 2002/160040691/01/000 | C55: Active | D55: 43783 | E55: 44148 | F55: Marine | G55: Vinay | H55: Ahmedabad | I55: Marine | J55: Renewal | K55: 18562.5 | L55: 43783 | M55: Brokerage | N55: Renewal | P55: 43852
A56: q | B56: 2002/E/107876781/03/000 | C56: Active | D56: 43381 | E56: 43745 | F56: Marine | G56: Vinay | H56: Ahmedabad | I56: Marine | J56: Renewal | K56: 3526.88 | L56: 43746 | M56: Brokerage | N56: Renewal | P56: 43852
A57: q | B57: 2002/E/1078781/02/000 | C57: Active | D57: 43016 | E57: 43380 | F57: Marine | G57: Juli | H57: Ahmedabad | I57: Marine | J57: Renewal | K57: 34950.98 | L57: 43016 | M57: Brokerage | N57: Inception | P57: 43852
A58: q | B58: 22214272 | C58: Active | D58: 43040 | E58: 43404 | F58: Marine | G58: Juli | H58: Ahmedabad | I58: Marine | J58: Renewal | K58: 55687.5 | L58: 43040 | M58: Brokerage | N58: Inception | P58: 43852
A59: R | B59: '14220011190100000062 | C59: Active | D59: 43567 | E59: 43932 | F59: Fire | G59: Raju Kumar | H59: Ahmedabad | I59: Property / BI | J59: Renewal | K59: 5187.31 | L59: 43567 | M59: Brokerage | N59: Inception | P59: 43852
A60: o | B60: 2690000138 04 | C60: Active | D60: 43337 | E60: 43701 | F60: Fire | G60: Vinay | H60: Ahmedabad | I60: Property / BI | J60: Cross Sell | K60: 2116.48 | L60: 43337 | M60: Brokerage | N60: Inception | P60: 43852
A61: o | B61: 2690000337 03 | C61: Active | D61: 43434 | E61: 43798 | F61: Fire | G61: Vinay | H61: Ahmedabad | I61: Property / BI | J61: Renewal | K61: 810.28 | L61: 43434 | M61: Brokerage | N61: Inception | P61: 43852
A62: T | B62: 30003393 | C62: Active | D62: 43586 | E62: 43951 | F62: Miscellaneous | G62: Ketan Jain | H62: Ahmedabad | I62: Trade Credit &amp; Political Risk | J62: New | K62: 379836.08 | L62: 43586 | M62: Brokerage | N62: Inception | P62: 43852
A63: T | B63: OG-18-2202-3315-00000028 | C63: Active | D63: 43555 | E63: 43920 | F63: Liability | G63: Ketan Jain | H63: Ahmedabad | I63: Liability | J63: Cross Sell | K63: 28087.5 | L63: 43555 | M63: Brokerage | N63: Inception | P63: 43852
A64: U | B64: '23060036180200000022 | C64: Active | D64: 43466 | E64: 43830 | F64: Liability | G64: Vinay | H64: Ahmedabad | I64: Liability | J64: Renewal | K64: 137500 | L64: 43466 | M64: Brokerage | N64: Inception | P64: 43852
A65: U | B65: '2999202466609300000 | C65: Active | D65: 43377 | E65: 43741 | F65: Liability | G65: Vinay | H65: Ahmedabad | I65: Liability | J65: Cross Sell | K65: 18750 | L65: 43377 | M65: Brokerage | N65: Inception | P65: 43852
A66: U | B66: '2999203175548500000 | C66: Active | D66: 43801 | E66: 44166 | F66: Liability | G66: Vinay | H66: Ahmedabad | I66: Liability | J66: Renewal | K66: 8125 | L66: 43801 | M66: Brokerage | N66: Inception | P66: 43852
A67: V | B67: 141400/11/2018/737 | C67: Active | D67: 43160 | E67: 43524 | F67: Fire | G67: Juli | H67: Ahmedabad | I67: Small Medium Enterpries (SME) | J67: New | K67: 116487.04 | L67: 43160 | M67: Brokerage | N67: Inception | P67: 43852
A68: V | B68: 141400/11/2018/738 | C68: Active | D68: 43160 | E68: 43524 | F68: Fire | G68: Juli | H68: Ahmedabad | I68: Small Medium Enterpries (SME) | J68: New | K68: 2988.62 | L68: 43160 | M68: Brokerage | N68: Inception | P68: 43852
A69: V | B69: 141400/44/2018/101 | C69: Active | D69: 43160 | E69: 43524 | F69: Miscellaneous | G69: Juli | H69: Ahmedabad | I69: Small Medium Enterpries (SME) | J69: New | K69: 14627.5 | L69: 43160 | M69: Brokerage | N69: Inception | P69: 43852
A70: V | B70: 141400/44/2018/102 | C70: Active | D70: 43160 | E70: 43524 | F70: Miscellaneous | G70: Juli | H70: Ahmedabad | I70: Small Medium Enterpries (SME) | J70: New | K70: 2020.5 | L70: 43160 | M70: Brokerage | N70: Inception | P70: 43852
A71: V | B71: 141400/48/2018/2149 | C71: Active | D71: 43160 | E71: 43524 | F71: Miscellaneous | G71: Juli | H71: Ahmedabad | I71: Small Medium Enterpries (SME) | J71: New | K71: 625.13 | L71: 43160 | M71: Brokerage | N71: Inception | P71: 43852
A72: V | B72: 141400/48/2018/2150 | C72: Active | D72: 43160 | E72: 43524 | F72: Miscellaneous | G72: Juli | H72: Ahmedabad | I72: Small Medium Enterpries (SME) | J72: Cross Sell | K72: 417 | L72: 43160 | M72: Brokerage | N72: Inception | P72: 43852
A73: V | B73: 141400/48/2018/2237 | C73: Active | D73: 43160 | E73: 43524 | F73: Miscellaneous | G73: Juli | H73: Ahmedabad | I73: Small Medium Enterpries (SME) | J73: New | K73: 687.63 | L73: 43160 | M73: Brokerage | N73: Inception | P73: 43852
A74: V | B74: 141400/48/2018/2238 | C74: Active | D74: 43160 | E74: 43524 | F74: Liability | G74: Juli | H74: Ahmedabad | I74: Small Medium Enterpries (SME) | J74: New | K74: 374.88 | L74: 43160 | M74: Brokerage | N74: Inception | P74: 43852
... A78: AA | B78: '91000036191700000002 | C78: Active | D78: 43608 | E78: 43973 | F78: Liability | G78: Vinay | H78: Ahmedabad | I78: Liability | J78: Renewal | K78: 131250 | L78: 43608 | M78: Brokerage | N78: Inception | P78: 43852
A79: BB | B79: 302102591 | C79: Inactive | D79: 43348 | E79: 43712 | F79: Miscellaneous | G79: Animesh Rawat | H79: Ahmedabad | I79: Global Client Network (GNB Inward) | J79: Renewal | K79: 6058.38 | L79: 43348 | M79: Brokerage | N79: Inception | P79: 43852
A80: BB | B80: 668111383 | C80: Active | D80: 43025 | E80: 43389 | F80: Fire | G80: Animesh Rawat | H80: Ahmedabad | I80: Global Client Network (GNB Inward) | J80: Renewal | K80: 29608.99 | L80: 43025 | M80: Brokerage | N80: Inception | P80: 43852
A81: BB | B81: 668111383 | C81: Active | D81: 43025 | E81: 43389 | F81: Fire | G81: Animesh Rawat | H81: Ahmedabad | I81: Global Client Network (GNB Inward) | J81: Renewal | K81: 29638.4 | L81: 43025 | M81: Brokerage | N81: Inception | P81: 43852
A82: BB | B82: 668111383 | C82: Active | D82: 43025 | E82: 43389 | F82: Fire | G82: Animesh Rawat | H82: Ahmedabad | I82: Global Client Network (GNB Inward) | J82: Renewal | K82: 237107.16 | L82: 43025 | M82: Brokerage | N82: Inception | P82: 43852
A83: BB | B83: 0668111383 05 | C83: Active | D83: 43390 | E83: 43754 | F83: Miscellaneous | G83: Animesh Rawat | H83: Ahmedabad | I83: Global Client Network (GNB Inward) | J83: Renewal | K83: 295501.76 | L83: 43390 | M83: Brokerage | N83: Inception | P83: 43852
A84: BB | B84: 2250015394 | C84: Active | D84: 43713 | E84: 44078 | F84: Miscellaneous | G84: Animesh Rawat | H84: Ahmedabad | I84: Global Client Network (GNB Inward) | J84: Renewal | K84: 5612.25 | L84: 43713 | M84: Brokerage | N84: Renewal | P84: 43852
A85: BB | B85: 2309002394 | C85: Active | D85: 43101 | E85: 43465 | F85: Liability | G85: Animesh Rawat | H85: Ahmedabad | I85: Global Client Network (GNB Inward) | J85: Renewal | K85: 30875 | L85: 43101 | M85: Brokerage | N85: Inception | P85: 43852
A86: BB | B86: 3.114203e+18 | C86: Active | D86: 43703 | E86: 44068 | F86: Miscellaneous | G86: Animesh Rawat | H86: Ahmedabad | I86: Global Client Network (GNB Inward) | J86: Cross Sell | K86: 7022.25 | L86: 43703 | M86: Brokerage | N86: Inception | P86: 43852
A87: BB | B87: OG-19-2202-1018-00000053 | C87: Active | D87: 43466 | E87: 43830 | F87: Marine | G87: Animesh Rawat | H87: Ahmedabad | I87: Global Client Network (GNB Inward) | J87: Cross Sell | K87: 77787.36 | L87: 43466 | M87: Brokerage | N87: Inception | P87: 43852
A88: BB | B88: OG-19-2202-3383-00000008 | C88: Active | D88: 43466 | E88: 43830 | F88: Liability | G88: Animesh Rawat | H88: Ahmedabad | I88: Global Client Network (GNB Inward) | J88: Cross Sell | K88: 30048.08 | L88: 43466 | M88: Brokerage | N88: Inception | P88: 43852
A89: BB | B89: PROHLN000242106 | C89: Active | D89: 43724 | E89: 44089 | F89: Employee Benefits | G89: Animesh Rawat | H89: Ahmedabad | I89: Global Client Network (GNB Inward) | J89: Cross Sell | K89: 7690.95 | L89: 43724 | M89: Brokerage | N89: Inception | P89: 43852
A90: BB | B90: 1.2030046e+19 | C90: Inactive | D90: 43322 | E90: 43686 | F90: Miscellaneous | G90: Shivani Sharma | H90: Ahmedabad | I90: Global Client Network (GNB Inward) | J90: Renewal | K90: 86400 | L90: 43322 | M90: Brokerage | N90: Inception | P90: 43852
A91: BB | B91: 1.2030046e+19 | C91: Inactive | D91: 43322 | E91: 43686 | F91: Miscellaneous | G91: Shivani Sharma | H91: Ahmedabad | I91: Global Client Network (GNB Inward) | J91: Renewal | K91: 345705 | L91: 43322 | M91: Brokerage | N91: Inception | P91: 43852
A92: BB | B92: 1.2030046e+19 | C92: Active | D92: 43687 | E92: 44052 | F92: Miscellaneous | G92: Animesh Rawat | H92: Ahmedabad | I92: Global Client Network (GNB Inward) | J92: Renewal | K92: 77400 | L92: 43687 | M92: Brokerage | N92: Renewal | P92: 43852
A93: BB | B93: 1.2030046e+19 | C93: Active | D93: 43687 | E93: 44052 | F93: Miscellaneous | G93: Animesh Rawat | H93: Ahmedabad | I93: Global Client Network (GNB Inward) | J93: Renewal | K93: 302811.08 | L93: 43687 | M93: Brokerage | N93: Renewal | P93: 43852
A94: BB | B94: P0319200002/9999/100065 | C94: Active | D94: 43282 | E94: 43646 | F94: Liability | G94: Shivani Sharma | H94: Ahmedabad | I94: Global Client Network (GNB Inward) | J94: Renewal | K94: 1183.38 | L94: 43282 | M94: Brokerage | N94: Inception | P94: 43852
A95: S | B95: 2018-F0541357-FRE | C95: Active | D95: 43359 | E95: 43723 | F95: Fire | G95: Vinay | H95: Ahmedabad | I95: Property / BI | J95: Renewal | K95: 33977.82 | L95: 43359 | M95: Brokerage | N95: Inception | P95: 43852
A96: BB | B96: '11120044170300000009 | C96: Active | D96: 43066 | E96: 44161 | F96: Engineering | G96: Raju Kumar | H96: Ahmedabad | I96: Construction, Power & Infrastructure | J96: Cross Sell | K96: 25303.02 | L96: 43247 | M96: Brokerage | N96: Inception | P96: 43852
A97: BB | B97: '11120044170300000009 | C97: Active | D97: 43066 | E97: 44161 | F97: Engineering | G97: Raju Kumar | H97: Ahmedabad | I97: Construction, Power & Infrastructure | J97: Cross Sell | K97: 25302.96 | L97: 43612 | M97: Brokerage | N97: Inception | P97: 43852
A98: BB | B98: '11120044170300000009 | C98: Active | D98: 43066 | E98: 44161 | F98: Engineering | G98: Raju Kumar | H98: Ahmedabad | I98: Construction, Power & Infrastructure | J98: Cross Sell | K98: 25302.96 | L98: 43704 | M98: Brokerage | N98: Inception | P98: 43852
A99: BB | B99: '11120044170300000009 | C99: Active | D99: 43066 | E99: 44161 | F99: Engineering | G99: Raju Kumar | H99: Ahmedabad | I99: Construction, Power & Infrastructure | J99: Cross Sell | K99: 25302.96 | L99: 43796 | M99: Brokerage | N99: Inception | P99: 43852
A100: BB | B100: '11120044170300000009 | C100: Active | D100: 43066 | E100: 44161 | F100: Engineering | G100: Raju Kumar | H100: Ahmedabad | I100: Construction, Power & Infrastructure | J100: Cross Sell | K100: 25302.96 | L100: 43888 | M100: Brokerage | N100: Inception | P100: 43852
A101: BB | B101: '11120044170300000009 | C101: Active | D101: 43066 | E101: 44161 | F101: Engineering | G101: Raju Kumar | H101: Ahmedabad | I101: Construction, Power & Infrastructure | J101: Cross Sell | K101: 25302.96 | L101: 43978 | M101: Brokerage | N101: Inception | P101: 43852
A102: BB | B102: '11120044170300000009 | C102: Active | D102: 43066 | E102: 44161 | F102: Engineering | G102: Raju Kumar | H102: Ahmedabad | I102: Construction, Power & Infrastructure | J102: Cross Sell | K102: 25302.96 | L102: 43339 | M102: Brokerage | N102: Inception | P102: 43852
A103: BB | B103: '11120044170300000009 | C103: Active | D103: 43066 | E103: 44161 | F103: Engineering | G103: Raju Kumar | H103: Ahmedabad | I103: Construction, Power & Infrastructure | J103: Cross Sell | K103: 25302.96 | L103: 43431 | M103: Brokerage | N103: Inception | P103: 43852
...

Sheet fees
A1: client_name | B1: branch_name | C1: solution_group | D1: Account Executive | E1: income_class | F1: Amount | G1: income_due_date | H1: revenue_transaction_type
A2: A | B2: Ahmedabad | C2: Construction, Power & Infrastructure | D2: Nishant Sharma | E2: Cross Sell | F2: 139240 | G2: 43663 | H2: Fees
A3: A | B3: Ahmedabad | C3: Construction, Power & Infrastructure | D3: Nishant Sharma | E3: Cross Sell | F3: 139240 | G3: 43486 | H3: Fees
A4: B | B4: Ahmedabad | C4: GL Client Network (GNB Inward) | D4: Divya Dhingra | E4: Renewal | F4: 2200 | G4: 43819 | H4: Fees
A5: C | B5: Ahmedabad | C5: GL Client Network (GNB Inward) | D5: Divya Dhingra | E5: Renewal | F5: 4500 | G5: 43490 | H5: Fees
A6: D | B6: Ahmedabad | C6: Construction, Power & Infrastructure | D6: Nishant Sharma | E6: Cross Sell | F6: 118000 | G6: 43539 | H6: Fees
A7: E | B7: Ahmedabad | C7: GL Client Network (GNB Inward) | D7: Divya Dhingra | E7: Renewal | F7: 2800 | G7: 43613 | H7: Fees
A8: F | B8: Ahmedabad | C8: GL Client Network (GNB Inward) | D8: Divya Dhingra | E8: Renewal | F8: 3241 | G8: 43490 | H8: Fees
A9: G | B9: Ahmedabad | C9: Liability | D9: Neel Jain | E9: New | F9: 100000 | G9: 43565 | H9: Fees
A10: H | B10: Ahmedabad | C10: GL Client Network (GNB Inward) | D10: Divya Dhingra | E10: Renewal | F10: 5310 | G10: 43805 | H10: Fees

Sheet Individual bdgt 
A1: Branch | B1: Employee Name | C1: New Role2 | D1: New Budget | E1: Cross sell bugdet | F1: Renewal Budget
A2: Ahmedabad | B2: Anil Tailor | C2: Hunter & Farmer | D2: 0 | E2: 250000 | F2: 1500000
A3: Ahmedabad | B3: Ankita Shah | C3: Servicer
A4: Ahmedabad | B4: Divya Dhingra | C4: Servicer | D4: 0 | E4: 0 | F4: 0
A5: Ahmedabad | B5: Neel Jain | C5: BH | D5: 1000000 | E5: 500000 | F5: 1010000
A6: Ahmedabad | B6: Nishant Sharma | C6: Hunter & Farmer | D6: 1250000 | E6: 3500000 | F6: 750000
A7: Ahmedabad | B7: Ritesh Sharma | C7: Servicer Claims
A8: Ahmedabad | B8: Shloka Shelat | C8: Hunter & Farmer | D8: 500000 | E8: 1250000 | F8: 500000
A9: Ahmedabad | B9: Shobhit Agarwal | C9: Hunter & Farmer | D9: 1350000 | E9: 750000 | F9: 750000
A10: Ahmedabad | B10: Vaibhav K Thaker | C10: Servicer | D10: 0 | E10: 0 | F10: 0
A11: Ahmedabad | B11: Vidit Shah | C11: Farmer & Servicer | D11: 0 | E11: 1040000 | F11: 5010000

Sheet Invoice
A1: invoice_number | B1: invoice_date | C1: revenue_transaction_type | D1: branch_name | E1: solution_group | F1: Account Executive | G1: income_class | H1: client_name | I1: policy_number | J1: Amount | K1: income_due_date
A2: 1900001087 | B2: 43566 | C2: Fees | D2: Ahmedabad | E2: Liability | F2: Neel Jain | G2: New | H2: I | J2: 84746 | K2: 43565
A3: 1900001106 | B3: 43602 | C3: Brokerage | D3: Ahmedabad | E3: Global Client Network (GNB Inward) | F3: Divya Dhingra | G3: Renewal | H3: M | I3: 2.4142021e+18 | J3: 86724 | K3: 43466
A4: 1900001110 | B4: 43602 | C4: Brokerage | D4: Ahmedabad | E4: Global Client Network (GNB Inward) | F4: Divya Dhingra | G4: Renewal | H4: S | I4: OG-19-2202-1018-00000060 | J4: 148500 | K4: 43525
A5: 1900001136 | B5: 43615 | C5: Brokerage | D5: Ahmedabad | E5: Global Client Network (GNB Inward) | F5: Divya Dhingra | G5: Cross Sell | H5: V | I5: OG-19-2202-3383-00000010 | J5: 12019 | K5: 43466
A6: 1900001164 | B6: 43627 | C6: Brokerage | D6: Ahmedabad | E6: Global Client Network (GNB Inward) | F6: Divya Dhingra | G6: Renewal | H6: I | I6: 020P000098803000 | J6: 12500 | K6: 43522
A7: 1900001165 | B7: 43627 | C7: Brokerage | D7: Ahmedabad | E7: Employee Benefits (EB) | F7: Shloka Shelat | G7: New | H7: I | I7: 206314000000 | J7: 58300 | K7: 43512
A8: 1900001167 | B8: 43629 | C8: Brokerage | D8: Ahmedabad | E8: Global Client Network (GNB Inward) | F8: Divya Dhingra | G8: Cross Sell | H8: A | I8: OG-19-2202-3383-00000009 | J8: 12019 | K8: 43466
A9: 1900001168 | B9: 43629 | C9: Brokerage | D9: Ahmedabad | E9: Global Client Network (GNB Inward) | F9: Divya Dhingra | G9: Cross Sell | H9: C | I9: OG-19-2202-3383-00000008 | J9: 30048 | K9: 43466
A10: 1900001169 | B10: 43629 | C10: Brokerage | D10: Ahmedabad | E10: Global Client Network (GNB Inward) | F10: Divya Dhingra | G10: Renewal | H10: P | I10: 3.1242016e+18 | J10: 14394 | K10: 43467
A11: 1900001282 | B11: 43659 | C11: Brokerage | D11: Ahmedabad | E11: Employee Benefits (EB) | F11: Ankita Shah | H11: S | I11: H0048996 | J11: 32392 | K11: 43595
A12: 1900001293 | B12: 43662 | C12: Brokerage | D12: Ahmedabad | E12: Liability | F12: Vidit Shah | G12: Cross Sell | H12: M | I12: '001P000202300000 | J12: 162500 | K12: 43560
A13: 1900001294 | B13: 43662 | C13: Brokerage | D13: Ahmedabad | E13: Liability | F13: Vidit Shah | G13: Cross Sell | H13: M | I13: '001P000203500000 | J13: 250000 | K13: 43573
A14: 1900001304 | B14: 43663 | C14: Brokerage | D14: Ahmedabad | E14: Global Client Network (GNB Inward) | F14: Divya Dhingra | G14: Cross Sell | H14: I | I14: 2280082714 | J14: 2646 | K14: 43535
A15: 1900001305 | B15: 43663 | C15: Brokerage | D15: Ahmedabad | E15: Global Client Network (GNB Inward) | F15: Divya Dhingra | H15: F | I15: 8502066 | J15: 18150 | K15: 43468
A16: 1900001306 | B16: 43663 | C16: Brokerage | D16: Ahmedabad | E16: Liability | F16: Nishant Sharma | G16: Cross Sell | H16: L | I16: 2999202758217600000" | J16: 60025 | K16: 43577
A17: 1900001308 | B17: 43663 | C17: Brokerage | D17: Ahmedabad | E17: Construction, Power & Infrastructure | F17: Shloka Shelat | G17: Cross Sell | H17: G | I17: 9.9000044e+19 | J17: 134736 | K17: 43580
A18: 1900001342 | B18: 43669 | C18: Brokerage | D18: Ahmedabad | E18: Employee Benefits (EB) | F18: Ankita Shah | G18: Renewal | H18: S | I18: H0048996 | J18: 914999 | K18: 43466
A19: 1900001354 | B19: 43670 | C19: Brokerage | D19: Ahmedabad | E19: Global Client Network (GNB Inward) | F19: Divya Dhingra | G19: Cross Sell | H19: P | I19: 3.1142027e+18 | J19: 2942 | K19: 43566
A20: 1900001355 | B20: 43670 | C20: Brokerage | D20: Ahmedabad | E20: Global Client Network (GNB Inward) | F20: Divya Dhingra | G20: Cross Sell | H20: M | I20: OG-19-2202-1002-00001981 | J20: 6740 | K20: 43528
A21: 1900001356 | B21: 43670 | C21: Brokerage | D21: Ahmedabad | E21: Global Client Network (GNB Inward) | F21: Divya Dhingra | G21: Renewal | H21: M | I21: OG-19-2202-1002-00001901 | J21: 6740 | K21: 43513
A22: 1900001361 | B22: 43673 | C22: Brokerage | D22: Ahmedabad | E22: Liability | F22: Shloka Shelat | G22: Cross Sell | H22: T | I22: 41045707 | J22: 74250 | K22: 43556
A23: 1900001376 | B23: 43675 | C23: Brokerage | D23: Ahmedabad | E23: Employee Benefits (EB) | F23: Ankita Shah | H23: S | I23: H0056637 | J23: 1614 | K23: 43535
A24: 1900001377 | B24: 43675 | C24: Brokerage | D24: Ahmedabad | E24: Marine | F24: Vidit Shah | G24: Cross Sell | H24: P | I24: '99000021180100000013 | J24: 11540 | K24: 43494
A25: 1900001385 | B25: 43677 | C25: Brokerage | D25: Ahmedabad | E25: Global Client Network (GNB Inward) | F25: Divya Dhingra | H25: S | I25: P0019200001/9999/100301 | J25: 2140 | K25: 43495
A26: 1900001388 | B26: 43677 | C26: Brokerage | D26: Ahmedabad | E26: Global Client Network (GNB Inward) | F26: Divya Dhingra | G26: Renewal | H26: F | I26: 0000000008502066-01 | J26: 45375 | K26: 43525
A27: 1900001390 | B27: 43677 | C27: Brokerage | D27: Ahmedabad | E27: Global Client Network (GNB Inward) | F27: Divya Dhingra | G27: Cross Sell | H27: M | I27: 32119154 | J27: 11593 | K27: 43556
A28: 1900001392 | B28: 43677 | C28: Brokerage | D28: Ahmedabad | E28: Employee Benefits (EB) | F28: Ankita Shah | H28: S | I28: H0048996 | J28: 46995 | K28: 43494
A29: 1900001393 | B29: 43677 | C29: Brokerage | D29: Ahmedabad | E29: Global Client Network (GNB Inward) | F29: Divya Dhingra | G29: Cross Sell | H29: M | I29: OG-19-2202-4010-00002245 | J29: 529 | K29: 43514
A30: 1900001394 | B30: 43677 | C30: Brokerage | D30: Ahmedabad | E30: Global Client Network (GNB Inward) | F30: Divya Dhingra | G30: Renewal | H30: B | I30: OG-19-2202-1018-00000059 | J30: 18563 | K30: 43525
A31: 1900001396 | B31: 43677 | C31: Brokerage | D31: Ahmedabad | E31: Employee Benefits (EB) | F31: Ankita Shah | H31: S | I31: H0048996 | J31: 27435 | K31: 43488
A32: 1900001397 | B32: 43677 | C32: Brokerage | D32: Ahmedabad | E32: Employee Benefits (EB) | F32: Ankita Shah | G32: Renewal | H32: W | I32: 505373-01 | J32: 25336 | K32: 43522
A33: 1900001398 | B33: 43677 | C33: Brokerage | D33: Ahmedabad | E33: Employee Benefits (EB) | F33: Ankita Shah | H33: W | I33: H0067187 | J33: 10772 | K33: 43538
A34: 1900001403 | B34: 43677 | C34: Brokerage | D34: Ahmedabad | E34: Employee Benefits (EB) | F34: Ankita Shah | H34: W | I34: H0067187 | J34: 9283 | K34: 43573
A35: 1900001404 | B35: 43677 | C35: Brokerage | D35: Ahmedabad | E35: Employee Benefits (EB) | F35: Ankita Shah | H35: W | I35: H0067187 | J35: 6903 | K35: 43615
A36: 1900001405 | B36: 43677 | C36: Brokerage | D36: Ahmedabad | E36: Construction, Power & Infrastructure | F36: Vidit Shah | G36: Renewal | H36: P | I36: '99000044190700000001 | J36: 90663 | K36: 43556
A37: 1900001583 | B37: 43691 | C37: Brokerage | D37: Ahmedabad | E37: Employee Benefits (EB) | F37: Ankita Shah | G37: Renewal | H37: T | I37: 100200080123/01/00 | J37: 156000 | K37: 43469
A38: 1900001602 | B38: 43694 | C38: Brokerage | D38: Ahmedabad | E38: Global Client Network (GNB Inward) | F38: Divya Dhingra | G38: Cross Sell | H38: V | I38: OG-19-2202-1018-00000054 | J38: 21157 | K38: 43466
A39: 1900001603 | B39: 43694 | C39: Brokerage | D39: Ahmedabad | E39: Global Client Network (GNB Inward) | F39: Divya Dhingra | G39: Cross Sell | H39: C | I39: OG-19-2202-1018-00000053 | J39: 77787 | K39: 43466
A40: 1900001604 | B40: 43694 | C40: Brokerage | D40: Ahmedabad | E40: Global Client Network (GNB Inward) | F40: Divya Dhingra | G40: Cross Sell | H40: M | I40: OG-19-2202-4001-00011127 | J40: 8468 | K40: 43514
A41: 1900001605 | B41: 43694 | C41: Brokerage | D41: Ahmedabad | E41: Employee Benefits (EB) | F41: Ankita Shah | G41: Renewal | H41: A | I41: 237164239 00 | J41: 1825 | K41: 43497
A42: 1900001606 | B42: 43694 | C42: Brokerage | D42: Ahmedabad | E42: Employee Benefits (EB) | F42: Ankita Shah | G42: Renewal | H42: W | I42: H0067187 | J42: 329250 | K42: 43524
A43: 1900001607 | B43: 43694 | C43: Brokerage | D43: Ahmedabad | E43: Global Client Network (GNB Inward) | F43: Divya Dhingra | G43: Renewal | H43: M | I43: 304003763 | J43: 344794 | K43: 43556
A44: 1900001608 | B44: 43694 | C44: Brokerage | D44: Ahmedabad | E44: Global Client Network (GNB Inward) | F44: Divya Dhingra | G44: Renewal | H44: M | I44: 2304001082-01 | J44: 37500 | K44: 43556
A45: 1900001609 | B45: 43694 | C45: Brokerage | D45: Ahmedabad | E45: Employee Benefits (EB) | F45: Ankita Shah | G45: Renewal | H45: S | I45: H0056637 | J45: 49789 | K45: 43466
A46: 1900001610 | B46: 43694 | C46: Brokerage | D46: Ahmedabad | E46: Global Client Network (GNB Inward) | F46: Divya Dhingra | G46: Renewal | H46: G | I46: 0600010004 01 | J46: 64 | K46: 43540
A47: 1900001611 | B47: 43694 | C47: Brokerage | D47: Ahmedabad | E47: Global Client Network (GNB Inward) | F47: Divya Dhingra | G47: Renewal | H47: I | I47: 0000000008907502-01 | J47: 6250 | K47: 43520
A48: 1900002041 | B48: 43705 | C48: Brokerage | D48: Ahmedabad | E48: Trade Credit &amp; Political Risk | F48: Gautam Murkunde | G48: Renewal | H48: T | I48: 1.310005e+19 | J48: 124875 | K48: 43531
A49: 1900002042 | B49: 43705 | C49: Brokerage | D49: Ahmedabad | E49: Liability | F49: Shloka Shelat | G49: Cross Sell | H49: S | I49: 43190133 | J49: 7783 | K49: 43627
A50: 1900002043 | B50: 43705 | C50: Brokerage | D50: Ahmedabad | E50: Liability | F50: Shloka Shelat | G50: Cross Sell | H50: S | I50: 43189992 | J50: 7835 | K50: 43626
A51: 1900002044 | B51: 43705 | C51: Brokerage | D51: Ahmedabad | E51: Liability | F51: Shloka Shelat | G51: New | H51: F | I51: 41045400 | J51: 70125 | K51: 43543
A52: 1900002045 | B52: 43705 | C52: Brokerage | D52: Ahmedabad | E52: Liability | F52: Shloka Shelat | G52: New | H52: F | I52: 41045403 | J52: 70125 | K52: 43543
A53: 1900002046 | B53: 43705 | C53: Brokerage | D53: Ahmedabad | E53: Property / BI | F53: Vidit Shah | G53: Renewal | H53: P | I53: '99000046192400000001 | J53: 60229 | K53: 43556
A54: 1900002047 | B54: 43705 | C54: Brokerage | D54: Ahmedabad | E54: Property / BI | F54: Vidit Shah | G54: Renewal | H54: P | I54: '99000011180100000303 | J54: 98931 | K54: 43481
A55: 1900002048 | B55: 43705 | C55: Brokerage | D55: Ahmedabad | E55: Global Client Network (GNB Inward) | F55: Divya Dhingra | G55: Cross Sell | H55: A | I55: OG-19-2202-1018-00000055 | J55: 21769 | K55: 43466
A56: 1900002049 | B56: 43705 | C56: Brokerage | D56: Ahmedabad | E56: Global Client Network (GNB Inward) | F56: Divya Dhingra | G56: Renewal | H56: G | I56: 0640002231 04 | J56: 65369 | K56: 43572
A57: 1900002050 | B57: 43705 | C57: Brokerage | D57: Ahmedabad | E57: Global Client Network (GNB Inward) | F57: Divya Dhingra | G57: Renewal | H57: D | I57: 304003761 | J57: 5206 | K57: 43556
A58: 1900002051 | B58: 43705 | C58: Brokerage | D58: Ahmedabad | E58: Global Client Network (GNB Inward) | F58: Divya Dhingra | G58: Renewal | H58: N | I58: 0301004265-1 | J58: 23750 | K58: 43533
A59: 1900002052 | B59: 43705 | C59: Brokerage | D59: Ahmedabad | E59: Global Client Network (GNB Inward) | F59: Divya Dhingra | G59: Renewal | H59: G | I59: 0600010004 02 | J59: 1557 | K59: 43571
A60: 1900002072 | B60: 43705 | C60: Brokerage | D60: Ahmedabad | E60: Construction, Power & Infrastructure | F60: Vidit Shah | G60: Cross Sell | H60: P | I60: '99000044190300000004 | J60: 40960 | K60: 43575
A61: 1900002229 | B61: 43708 | C61: Brokerage | D61: Ahmedabad | E61: Construction, Power & Infrastructure | F61: Vidit Shah | G61: Renewal | H61: P | I61: '99000044180700000012 | J61: 12055 | K61: 43510
A62: 1900002230 | B62: 43708 | C62: Brokerage | D62: Ahmedabad | E62: Property / BI | F62: Vidit Shah | G62: Renewal | H62: P | I62: '99000011180100000340 | J62: 131090 | K62: 43522
A63: 1900002232 | B63: 43708 | C63: Brokerage | D63: Ahmedabad | E63: Construction, Power & Infrastructure | F63: Vidit Shah | G63: Renewal | H63: P | I63: '99000044185800000014 | J63: 27069 | K63: 43510
A64: 1900002265 | B64: 43708 | C64: Brokerage | D64: Ahmedabad | E64: Global Client Network (GNB Inward) | F64: Divya Dhingra | G64: Renewal | H64: M | I64: 4092/151965577/01/000 | J64: 215165 | K64: 43556
A65: 1900002331 | B65: 43711 | C65: Brokerage | D65: Ahmedabad | E65: Global Client Network (GNB Inward) | F65: Divya Dhingra | G65: Renewal | H65: P | I65: 5002/131802941/02/000 | J65: 870 | K65: 43611
A66: 1900002384 | B66: 43713 | C66: Brokerage | D66: Ahmedabad | E66: Trade Credit &amp; Political Risk | F66: Gautam Murkunde | H66: M | I66: 2000010048 | J66: 8174 | K66: 43664
A67: 1900002387 | B67: 43713 | C67: Brokerage | D67: Ahmedabad | E67: Employee Benefits (EB) | F67: Ankita Shah | G67: Renewal | H67: S | I67: 4016/120415654/03/00 | J67: 22246 | K67: 43660
A68: 1900002458 | B68: 43717 | C68: Brokerage | D68: Ahmedabad | E68: Liability | F68: Shloka Shelat | G68: New | H68: P | I68: 43187020 | J68: 7451 | K68: 43577
A69: 1900002464 | B69: 43717 | C69: Brokerage | D69: Ahmedabad | E69: Employee Benefits (EB) | F69: Ankita Shah | H69: W | I69: H0067187 | J69: 7110 | K69: 43675
A70: 1900002472 | B70: 43717 | C70: Brokerage | D70: Ahmedabad | E70: Global Client Network (GNB Inward) | F70: Divya Dhingra | G70: Renewal | H70: P | I70: 4006/131284920/02/000 | J70: 692 | K70: 43600
A71: 1900002635 | B71: 43725 | C71: Brokerage | D71: Ahmedabad | E71: Trade Credit &amp; Political Risk | F71: Gautam Murkunde | G71: Renewal | H71: P | I71: NBI Domestic | J71: 65051 | K71: 43466
A72: 1900002636 | B72: 43725 | C72: Brokerage | D72: Ahmedabad | E72: Global Client Network (GNB Inward) | F72: Divya Dhingra | G72: Renewal | H72: M | I72: 4001/117090005/03/000 | J72: 1005 | K72: 43586
A73: 1900002637 | B73: 43725 | C73: Brokerage | D73: Ahmedabad | E73: Employee Benefits (EB) | F73: Ankita Shah | H73: W | I73: H0067187 | J73: 6259 | K73: 43637
A74: 1900002638 | B74: 43725 | C74: Brokerage | D74: Ahmedabad | E74: Employee Benefits (EB) | F74: Ankita Shah | H74: S | I74: H0048996 | J74: 9941 | K74: 43656
A75: 1900002639 | B75: 43725 | C75: Brokerage | D75: Ahmedabad | E75: Global Client Network (GNB Inward) | F75: Divya Dhingra | G75: Cross Sell | H75: M | I75: 2600015265 00 | J75: 9990 | K75: 43608
A76: 1900002640 | B76: 43725 | C76: Brokerage | D76: Ahmedabad | E76: Employee Benefits (EB) | F76: Ankita Shah | G76: Renewal | H76: B | I76: 4016/133979727/02/000 | J76: 74673 | K76: 43645
A77: 1900002880 | B77: 43728 | C77: Brokerage | D77: Ahmedabad | E77: Global Client Network (GNB Inward) | F77: Divya Dhingra | G77: Renewal | H77: G | I77: 0640002231 03 | J77: 4362 | K77: 43557
A78: 1900003129 | B78: 43738 | C78: Brokerage | D78: Ahmedabad | E78: Property / BI | F78: Vidit Shah | G78: Renewal | H78: P | I78: '99000011180100000339 | J78: 1610 | K78: 43510
A79: 1900003131 | B79: 43738 | C79: Brokerage | D79: Ahmedabad | E79: Global Client Network (GNB Inward) | F79: Divya Dhingra | G79: Renewal | H79: M | I79: 3.1142011e+18 | J79: 20166 | K79: 43647
A80: 1900003209 | B80: 43748 | C80: Brokerage | D80: Ahmedabad | E80: Employee Benefits (EB) | F80: Ankita Shah | G80: Renewal | H80: B | I80: 4005/134645920/02/000 | J80: 8605 | K80: 43645
A81: 1900003210 | B81: 43748 | C81: Brokerage | D81: Ahmedabad | E81: Employee Benefits (EB) | F81: Ankita Shah | G81: Renewal | H81: F | I81: 4101190600000030-00 | J81: 52500 | K81: 43602
A82: 1900003211 | B82: 43748 | C82: Brokerage | D82: Ahmedabad | E82: Liability | F82: Vidit Shah | G82: Cross Sell | H82: P | I82: '99000036181500000054 | J82: 21875 | K82: 43497
A83: 1900003212 | B83: 43748 | C83: Brokerage | D83: Ahmedabad | E83: Employee Benefits (EB) | F83: Ankita Shah | H83: S | I83: H0048996 | J83: 93906 | K83: 43531
A84: 1900003213 | B84: 43748 | C84: Brokerage | D84: Ahmedabad | E84: Employee Benefits (EB) | F84: Ankita Shah | G84: Renewal | H84: S | I84: 54407334 | J84: 23387 | K84: 43466
A85: 1900003214 | B85: 43748 | C85: Brokerage | D85: Ahmedabad | E85: Employee Benefits (EB) | F85: Ankita Shah | G85: Renewal | H85: S | I85: AG00059046000100 | J85: 3347 | K85: 43556
A86: 1900003404 | B86: 43755 | C86: Brokerage | D86: Ahmedabad | E86: Liability | F86: Nishant Sharma | G86: Cross Sell | H86: L | I86: 2.9992029e+18 | J86: 60025 | K86: 43654
A87: 1900003405 | B87: 43755 | C87: Brokerage | D87: Ahmedabad | E87: Marine | F87: Vidit Shah | G87: Renewal | H87: E | I87: 2412/202063061201000 | J87: 13613 | K87: 43472
A88: 1900003406 | B88: 43755 | C88: Brokerage | D88: Ahmedabad | E88: Employee Benefits (EB) | F88: Shobhit Agarwal | G88: New | H88: A | I88: 4101190700000015-00 | J88: 79834 | K88: 43641
A89: 1900003407 | B89: 43755 | C89: Brokerage | D89: Ahmedabad | E89: Liability | F89: Nishant Sharma | G89: Cross Sell | H89: L | I89: 2.9992029e+18 | J89: 60025 | K89: 43654
A90: 1900003928 | B90: 43781 | C90: Brokerage | D90: Ahmedabad | E90: Liability | F90: Shobhit Agarwal | G90: Cross Sell | H90: M | I90: 14055133 | J90: 63000 | K90: 43672
A91: 1900003930 | B91: 43781 | C91: Fees | D91: Ahmedabad | E91: Construction, Power & Infrastructure | F91: Nishant Sharma | G91: Cross Sell | H91: P | J91: 100000 | K91: 43663
A92: 1900003931 | B92: 43781 | C92: Fees | D92: Ahmedabad | E92: Construction, Power & Infrastructure | F92: Nishant Sharma | G92: Cross Sell | H92: P | J92: 100000 | K92: 43486
A93: 1900004171 | B93: 43795 | C93: Fees | D93: Ahmedabad | E93: Global Client Network (GNB Inward) | F93: Divya Dhingra | G93: Renewal | H93: S | J93: 254336 | K93: 43490
A94: 1900004173 | B94: 43795 | C94: Fees | D94: Ahmedabad | E94: Global Client Network (GNB Inward) | F94: Divya Dhingra | G94: Renewal | H94: G | J94: 266949 | K94: 43490
A95: 1900004220 | B95: 43802 | C95: Brokerage | D95: Ahmedabad | E95: Employee Benefits (EB) | F95: Ankita Shah | G95: Renewal | H95: W | I95: 54445288 | J95: 11111 | K95: 43524
A96: 1900004221 | B96: 43802 | C96: Brokerage | D96: Ahmedabad | E96: Construction, Power & Infrastructure | F96: Shloka Shelat | G96: Cross Sell | H96: S | I96: 9.9000044e+19 | J96: 3008 | K96: 43567
A97: 1900004376 | B97: 43804 | C97: Brokerage | D97: Ahmedabad | E97: Liability | F97: Shloka Shelat | G97: Cross Sell | H97: G | I97: 43193940 | J97: 6184 | K97: 43684
A98: 1900004378 | B98: 43804 | C98: Brokerage | D98: Ahmedabad | E98: Property / BI | F98: Shloka Shelat | G98: New | H98: K | I98: YB00020403000100 | J98: 1568 | K98: 43504
A99: 1900004380 | B99: 43804 | C99: Brokerage | D99: Ahmedabad | E99: Employee Benefits (EB) | F99: Ankita Shah | H99: S | I99: H0048996 | J99: 18901 | K99: 43722
A100: 1900004382 | B100: 43804 | C100: Brokerage | D100: Ahmedabad | E100: Employee Benefits (EB) | F100: Ankita Shah | H100: S | I100: H0048996 | J100: 27682 | K100: 43691
...

Sheet Opportunity
A1: opportunity_name | B1: opportunity_id | C1: Account Executive | D1: premium_amount | E1: revenue_amount | F1: closing_date | G1: stage | H1: branch | I1: specialty | J1: product_group | K1: product_sub_group | L1: risk_details
A2: EL-Group Mediclaim | B2: OPP1900001042 | C2: Animesh Rawat | D2: 8000000 | E2: 400000 | F2: 43782 | G2: Qualify Opportunity | H2: Ahmedabad | I2: Employee Benefits (EB) | J2: Employee Benefits | K2: Mediclaim | L2: Group Medical
A3: AL GPA | B3: OPP1900001047 | C3: Shivani Sharma | D3: 200000 | E3: 30000 | F3: 43921 | G3: Qualify Opportunity | H3: Ahmedabad | I3: Employee Benefits (EB) | J3: Employee Benefits | K3: Mediclaim | L3: Group Personal Accident
A4: BL - Marine STOP | B4: OPP1900001048 | C4: Shivani Sharma | D4: 0 | E4: 100000 | F4: 44012 | G4: Qualify Opportunity | H4: Ahmedabad | I4: Marine | J4: Marine | K4: Marine Hull | L4: Charterers' Liability Policy
A5: II-Marine | B5: OPP1900001050 | C5: Shivani Sharma | D5: 0 | E5: 100000 | F5: 43921 | G5: Qualify Opportunity | H5: Ahmedabad | I5: Marine | J5: Marine | K5: Marine Hull | L5: Charterers' Liability Policy
A6: PIL-Credit Insurance | B6: OPP1900001051 | C6: Shivani Sharma | D6: 1200000 | E6: 100000 | F6: 43921 | G6: Qualify Opportunity | H6: Ahmedabad | I6: Trade Credit &amp; Political Risk | J6: Miscellaneous | K6: Miscellaneous | L6: Trade Credit Insurance
A7: PIL-CGL | B7: OPP1900001052 | C7: Shivani Sharma | D7: 0 | E7: 100000 | F7: 43982 | G7: Qualify Opportunity | H7: Ahmedabad | I7: Liability | J7: Liability | K7: Financial Lines | L7: Commercial General Liability
A8: PIL -Marine | B8: OPP1900001053 | C8: Shivani Sharma | D8: 0 | E8: 100000 | F8: 43982 | G8: Qualify Opportunity | H8: Ahmedabad | I8: Marine | J8: Marine | K8: Marine Hull | L8: Charterers' Liability Policy
A9: SGL- GMC | B9: OPP1900001054 | C9: Shivani Sharma | D9: 0 | E9: 125000 | F9: 44012 | G9: Qualify Opportunity | H9: Ahmedabad | I9: Employee Benefits (EB) | J9: Employee Benefits | K9: Mediclaim | L9: Group Medical
A10: Sandesh - Marine | B10: OPP1900001055 | C10: Shivani Sharma | D10: 0 | E10: 100000 | F10: 43921 | G10: Qualify Opportunity | H10: Ahmedabad | I10: Marine | J10: Marine | K10: Marine Hull | L10: Charterers' Liability Policy
A11: VS.-Marine | B11: OPP1900001056 | C11: Shivani Sharma | D11: 0 | E11: 200000 | F11: 43921 | G11: Qualify Opportunity | H11: Ahmedabad | I11: Marine | J11: Marine | K11: Marine Hull | L11: Charterers' Liability Policy
A12: II - GMC | B12: OPP1900001057 | C12: Shivani Sharma | D12: 0 | E12: 75000 | F12: 43921 | G12: Qualify Opportunity | H12: Ahmedabad | I12: Employee Benefits (EB) | J12: Employee Benefits | K12: Mediclaim | L12: Group Medical
A13: II - GPA | B13: OPP1900001058 | C13: Shivani Sharma | D13: 0 | E13: 25000 | F13: 43921 | G13: Qualify Opportunity | H13: Ahmedabad | I13: Employee Benefits (EB) | J13: Employee Benefits | K13: Mediclaim | L13: Group Personal Accident
... A50: VS.-D & O | B50: OPP1900002104 | C50: Shivani Sharma | D50: 0 | E50: 50000 | F50: 43921 | G50: Qualify Opportunity | H50: Ahmedabad | I50: Liability | J50: Liability | K50: Financial Lines | L50: Director &amp; Officers / Management Liability

Sheet Meeting
A1: Account Executive | B1: branch_name | C1: meeting_date
A2: Abhinav Shivam | B2: Ahmedabad | C2: 43755
A3: Abhinav Shivam | B3: Ahmedabad | C3: 43755
A4: Abhinav Shivam | B4: Ahmedabad | C4: 43823
A5: Abhinav Shivam | B5: Ahmedabad | C5: 43833
A6: Abhinav Shivam | B6: Ahmedabad | C6: 43838
A7: Abhinav Shivam | B7: Ahmedabad | C7: 43838
A8: Abhinav Shivam | B8: Ahmedabad | C8: 43839
A9: Vinay | B9: Ahmedabad | C9: 43832
A10: Vinay | B10: Ahmedabad | C10: 43833
A11: Vinay | B11: Ahmedabad | C11: 43836
A12: Vinay | B12: Ahmedabad | C12: 43837
A13: Vinay | B13: Ahmedabad | C13: 43838
... A35: Mark | B35: Ahmedabad | C35: 43843

Sheet Multiple files
B2: Invoice | E2: Target Budget
B3: Row Labels | C3: Sum of Amount | E3: Sum of New Budget | F3: Sum of Cross sell bugdet | G3: Sum of Renewal Budget
B4: Cross Sell | C4: 3040813 | E4: 19673793 | F4: 20083111 | G4: 12319455
B5: New | C5: 827822
B6: Renewal | C6: 8394071
B7: Grand Total | C7: 12262706
E8: Achievement | G8: placed Ach% | H8: Invoice Ach%
B9: Brokerage | E9: Cross Sell | F9: =GETPIVOTDATA("[Measures].[Sum of Amount 2]",$B$10,"[Brokerage].[Income Class]","[Brokerage].[Income Class].&[Cross Sell]")+GETPIVOTDATA("[Measures].[Sum of Amount 3]",$B$18,"[Fees].[Income Class]","[Fees].[Income Class].&[Cross Sell]") -> #REF! | G9: =F9/GETPIVOTDATA("[Measures].[Sum of Cross sell bugdet]",$E$3) -> #REF! | H9: =GETPIVOTDATA("[Measures].[Sum of Amount]",$B$3,"[Invoice].[Imcome Class]","[Invoice].[Imcome Class].&[Cross Sell]")/GETPIVOTDATA("[Measures].[Sum of Cross sell bugdet]",$E$3) -> #REF!
B10: Row Labels | C10: Sum of Amount | E10: New | F10: =GETPIVOTDATA("[Measures].[Sum of Amount 2]",$B$10,"[Brokerage].[Income Class]","[Brokerage].[Income Class].&[New]")+GETPIVOTDATA("[Measures].[Sum of Amount 3]",$B$18,"[Fees].[Income Class]","[Fees].[Income Class].&[New]") -> #REF! | G10: =F10/GETPIVOTDATA("[Measures].[Sum of New Budget]",$E$3) -> #REF! | H10: =GETPIVOTDATA("[Measures].[Sum of Amount]",$B$3,"[Invoice].[Imcome Class]","[Invoice].[Imcome Class].&[New]")/GETPIVOTDATA("[Measures].[Sum of New Budget]",$E$3) -> #REF!
B11: (blank) | C11: 1558.76 | E11: Renewal | F11: =GETPIVOTDATA("[Measures].[Sum of Amount 2]",$B$10,"[Brokerage].[Income Class]","[Brokerage].[Income Class].&[Renewal]")+GETPIVOTDATA("[Measures].[Sum of Amount 3]",$B$18,"[Fees].[Income Class]","[Fees].[Income Class].&[Renewal]") -> #REF! | G11: =F11/GETPIVOTDATA("[Measures].[Sum of Renewal Budget]",$E$3) -> #REF! | H11: =GETPIVOTDATA("[Measures].[Sum of Amount]",$B$3,"[Invoice].[Imcome Class]","[Invoice].[Imcome Class].&[Renewal]")/GETPIVOTDATA("[Measures].[Sum of Renewal Budget]",$E$3) -> #REF!
B12: Cross Sell | C12: 12644773
B13: New | C13: 3431629.3
B14: Renewal | C14: 18489220
B15: Grand Total | C15: 34567181
B17: Fees
B18: Row Labels | C18: Sum of Amount
B19: Cross Sell | C19: 396480
B20: New | C20: 100000
B21: Renewal | C21: 18051
B22: Grand Total | C22: 514531

Sheet Placed achivement
A1: client_name | B1: policy_number | C1: policy_status | D1: policy_start_date | E1: policy_end_date | F1: product_group | G1: Account Executive | H1: branch_name | I1: solution_group | J1: income_class | K1: Amount | L1: income_due_date | M1: revenue_transaction_type | N1: renewal_status | O1: last_updated_date
A2: A | B2: 2414 2022 4088 1000 000 | C2: Active | D2: 43209 | E2: 43573 | F2: Marine | G2: Vinay | H2: Ahmedabad | I2: Marine | J2: Renewal | K2: 32186.72 | L2: 43209 | M2: Brokerage | N2: Inception | O2: 43852
A3: Amit | B3: 2.4142028e+18 | C3: Active | D3: 43586 | E3: 43951 | F3: Marine | G3: Abhinav Shivam | H3: Ahmedabad | I3: Marine | J3: New | K3: 23590.71 | L3: 43586 | M3: Brokerage | N3: Inception | O3: 43852
A4: B | B4: 0655001825 01 | C4: Inactive | D4: 43356 | E4: 43720 | F4: Fire | G4: Vinay | H4: Ahmedabad | I4: Construction, Power & Infrastructure | J4: Renewal | K4: 4611.96 | L4: 43356 | M4: Brokerage | N4: Inception | O4: 43852
A5: B | B5: 12139156 | C5: Active | D5: 43721 | E5: 44086 | F5: Fire | G5: Vinay | H5: Ahmedabad | I5: Construction, Power & Infrastructure | J5: Renewal | K5: 4975.41 | L5: 43721 | M5: Brokerage | N5: Renewal | O5: 43852
A6: B | B6: 2200090892 | C6: Active | D6: 43410 | E6: 43774 | F6: Miscellaneous | G6: Vinay | H6: Ahmedabad | I6: Liability | J6: Renewal | K6: 1198.88 | L6: 43410 | M6: Brokerage | N6: Inception | O6: 43852
A7: C | B7: 237164239 00 | C7: Active | D7: 43497 | E7: 43861 | F7: Employee Benefits | G7: Mark | H7: Ahmedabad | I7: Employee Benefits (EB) | J7: Renewal | K7: 1825.43 | L7: 43497 | M7: Brokerage | N7: Inception | O7: 43852
A8: D | B8: 4101190700000015-00 | C8: Active | D8: 43641 | E8: 44006 | F8: Employee Benefits | G8: Abhinav Shivam | H8: Ahmedabad | I8: Employee Benefits (EB) | J8: New | K8: 79833.6 | L8: 43641 | M8: Brokerage | N8: Endorsement | O8: 43852
A9: D | B9: 4101190700000015-00 | C9: Active | D9: 43641 | E9: 44006 | F9: Employee Benefits | G9: Abhinav Shivam | H9: Ahmedabad | I9: Employee Benefits (EB) | J9: New | K9: 11435.86 | L9: 43679 | M9: Brokerage | N9: Endorsement | O9: 43852
A10: E | B10: 2250010276 | C10: Active | D10: 43215 | E10: 43579 | F10: Miscellaneous | G10: Vinay | H10: Ahmedabad | I10: Employee Benefits (EB) | J10: Renewal | K10: 847.38 | L10: 43215 | M10: Brokerage | N10: Inception | O10: 43852
A11: E | B11: 2414 2022 1261 2200 000 | C11: Inactive | D11: 43215 | E11: 43579 | F11: Marine | G11: Vinay | H11: Ahmedabad | I11: Marine | J11: Renewal | K11: 9900 | L11: 43215 | M11: Brokerage | N11: Inception | O11: 43852
A12: E | B12: 2414 2026 2374 7800 000 | C12: Active | D12: 43476 | E12: 43840 | F12: Marine | G12: Vinay | H12: Ahmedabad | I12: Marine | J12: Renewal | K12: 8250 | L12: 43476 | M12: Brokerage | N12: Renewal | O12: 43852
A13: E | B13: 91001900000001 | C13: Active | D13: 43215 | E13: 43579 | F13: Fire | G13: Vinay | H13: Ahmedabad | I13: Property / BI | J13: Renewal | K13: 4093.2 | L13: 43215 | M13: Brokerage | N13: Inception | O13: 43852
A14: F | B14: 2280062933 | C14: Active | D14: 43605 | E14: 43970 | F14: Miscellaneous | G14: Vinay | H14: Ahmedabad | I14: Liability | J14: Renewal | K14: 8117 | L14: 43850 | M14: Brokerage | N14: Renewal | O14: 43852
A15: F | B15: LWC/I2568913/71/05/006144 | C15: Inactive | D15: 43240 | E15: 43604 | F15: Miscellaneous | G15: Vinay | H15: Ahmedabad | I15: Liability | J15: Renewal | K15: 6101.25 | L15: 43240 | M15: Brokerage | N15: Inception | O15: 43852
A16: G | B16: 0865074115 01 | C16: Active | D16: 43263 | E16: 43627 | F16: Marine | G16: Manish Sharma | H16: Ahmedabad | I16: Small Medium Enterpries (SME) | J16: Renewal | K16: 1980 | L16: 43263 | M16: Brokerage | N16: Endorsement | O16: 43852
A17: G | B17: 0865074115 01 | C17: Active | D17: 43263 | E17: 43627 | F17: Marine | G17: Manish Sharma | H17: Ahmedabad | I17: Small Medium Enterpries (SME) | J17: Renewal | K17: 1980 | L17: 43475 | M17: Brokerage | N17: Endorsement | O17: 43852
A18: H | B18: 3.114203e+18 | C18: Active | D18: 43703 | E18: 44068 | F18: Miscellaneous | G18: Animesh Rawat | H18: Ahmedabad | I18: Global Client Network (GNB Inward) | J18: Cross Sell | K18: 2089.25 | L18: 43703 | M18: Brokerage | N18: Inception | O18: 43852
A19: H | B19: OG-19-2202-1018-00000055 | C19: Active | D19: 43466 | E19: 43830 | F19: Marine | G19: Animesh Rawat | H19: Ahmedabad | I19: Global Client Network (GNB Inward) | J19: Cross Sell | K19: 21768.61 | L19: 43466 | M19: Brokerage | N19: Inception | O19: 43852
A20: H | B20: OG-19-2202-3383-00000009 | C20: Active | D20: 43466 | E20: 43830 | F20: Liability | G20: Animesh Rawat | H20: Ahmedabad | I20: Global Client Network (GNB Inward) | J20: Cross Sell | K20: 12019.2 | L20: 43466 | M20: Brokerage | N20: Inception | O20: 43852
A21: I | B21: 640002371 | C21: Active | D21: 43191 | E21: 43555 | F21: Miscellaneous | G21: Animesh Rawat | H21: Ahmedabad | I21: Global Client Network (GNB Inward) | J21: Renewal | K21: 66937.72 | L21: 43191 | M21: Brokerage | N21: Inception | O21: 43852
A22: I | B22: 0830017443 01 | C22: Active | D22: 43231 | E22: 43595 | F22: Marine | G22: Animesh Rawat | H22: Ahmedabad | I22: Global Client Network (GNB Inward) | J22: Renewal | K22: 78374.84 | L22: 43231 | M22: Brokerage | N22: Inception | O22: 43852
A23: I | B23: 180876-0000-00 | C23: Inactive | D23: 43191 | E23: 43555 | F23: Employee Benefits | G23: Mark | H23: Ahmedabad | I23: Employee Benefits (EB) | J23: Renewal | K23: 60000 | L23: 43191 | M23: Brokerage | N23: Inception | O23: 43852
A24: I | B24: 180876-0000-01 | C24: Active | D24: 43556 | E24: 43921 | F24: Employee Benefits | G24: Mark | H24: Ahmedabad | I24: Employee Benefits (EB) | J24: Renewal | K24: 60000 | L24: 43556 | M24: Brokerage | N24: Renewal | O24: 43852
A25: I | B25: 180876-0000-01 | C25: Active | D25: 43556 | E25: 43921 | F25: Employee Benefits | G25: Mark | H25: Ahmedabad | I25: Employee Benefits (EB) | J25: Renewal | K25: 60000 | L25: 43556 | M25: Brokerage | N25: Renewal | O25: 43852
A26: I | B26: 2250002346 | C26: Active | D26: 43191 | E26: 43555 | F26: Miscellaneous | G26: Animesh Rawat | H26: Ahmedabad | I26: Global Client Network (GNB Inward) | J26: Renewal | K26: 4715.63 | L26: 43191 | M26: Brokerage | N26: Inception | O26: 43852
A27: I | B27: 3.1242014e+18 | C27: Active | D27: 43191 | E27: 43555 | F27: Liability | G27: Animesh Rawat | H27: Ahmedabad | I27: Global Client Network (GNB Inward) | J27: Renewal | K27: 22755.25 | L27: 43191 | M27: Brokerage | N27: Inception | O27: 43852
A28: I | B28: P0119200001/9999/100017 | C28: Active | D28: 43191 | E28: 43555 | F28: Liability | G28: Shivani Sharma | H28: Ahmedabad | I28: Global Client Network (GNB Inward) | J28: Renewal | K28: 26443.63 | L28: 43191 | M28: Brokerage | N28: Inception | O28: 43852
A29: J | B29: 0865078325 00 | C29: Inactive | D29: 43196 | E29: 43560 | F29: Marine | G29: Vinay | H29: Ahmedabad | I29: Marine | J29: Renewal | K29: 49499.84 | L29: 43196 | M29: Brokerage | N29: Endorsement | O29: 43852
A30: J | B30: 0865078325 00 | C30: Inactive | D30: 43196 | E30: 43560 | F30: Marine | G30: Vinay | H30: Ahmedabad | I30: Marine | J30: Renewal | L30: 43384 | M30: Brokerage | N30: Endorsement | O30: 43852
A31: J | B31: 0865078325 00 | C31: Inactive | D31: 43196 | E31: 43560 | F31: Marine | G31: Vinay | H31: Ahmedabad | I31: Marine | J31: Renewal | K31: 16500 | L31: 43482 | M31: Brokerage | N31: Endorsement | O31: 43852
A32: J | B32: '0865078325 01 | C32: Active | D32: 43561 | E32: 43926 | F32: Marine | G32: Vinay | H32: Ahmedabad | I32: Marine | J32: Renewal | K32: 26400 | L32: 43561 | M32: Brokerage | N32: Renewal | O32: 43852
A33: J | B33: 0865080591 00 | C33: Active | D33: 43332 | E33: 43696 | F33: Marine | G33: Vinay | H33: Ahmedabad | I33: Marine | J33: Renewal | K33: 3300 | L33: 43332 | M33: Brokerage | N33: Inception | O33: 43852
A34: J | B34: 0865081032 00 | C34: Active | D34: 43354 | E34: 43718 | F34: Marine | G34: Vinay | H34: Ahmedabad | I34: Marine | J34: Renewal | K34: 1072.5 | L34: 43354 | M34: Brokerage | N34: Inception | O34: 43852
A35: J | B35: '310304111710000871 | C35: Active | D35: 43186 | E35: 43550 | F35: Fire | G35: Vinay | H35: Ahmedabad | I35: Property / BI | J35: Renewal | K35: 4002.46 | L35: 43186 | M35: Brokerage | N35: Inception | O35: 43852
A36: J | B36: 3.1030411e+17 | C36: Active | D36: 43326 | E36: 43690 | F36: Fire | G36: Vinay | H36: Ahmedabad | I36: Property / BI | J36: Renewal | K36: 1374.25 | L36: 43326 | M36: Brokerage | N36: Inception | O36: 43852
A37: J | B37: 3.1030459e+18 | C37: Active | D37: 43186 | E37: 43550 | F37: Fire | G37: Vinay | H37: Ahmedabad | I37: Property / BI | J37: Cross Sell | K37: 566.25 | L37: 43186 | M37: Brokerage | N37: Inception | O37: 43852
A38: J | B38: '310304591810000063 | C38: Active | D38: 43326 | E38: 43690 | F38: Miscellaneous | G38: Vinay | H38: Ahmedabad | I38: Property / BI | J38: Renewal | K38: 445 | L38: 43326 | M38: Brokerage | N38: Inception | O38: 43852
A39: K | B39: '310300111910000401 | C39: Active | D39: 43709 | E39: 44074 | F39: Fire | G39: Vinay | H39: Ahmedabad | I39: Property / BI | J39: Renewal | K39: 13114.95 | L39: 43709 | M39: Brokerage | N39: Renewal | O39: 43852
A40: K | B40: 3.1030411e+17 | C40: Inactive | D40: 43344 | E40: 43708 | F40: Fire | G40: Vinay | H40: Ahmedabad | I40: Property / BI | J40: Renewal | K40: 2049.42 | L40: 43344 | M40: Brokerage | N40: Inception | O40: 43852
A41: L | B41: 301002850 | C41: Active | D41: 43313 | E41: 43677 | F41: Liability | G41: Ketan Jain | H41: Ahmedabad | I41: Liability | J41: Renewal | K41: 61425 | L41: 43313 | M41: Brokerage | N41: Inception | O41: 43852
A42: M | B42: 2.4122019e+18 | C42: Active | D42: 43370 | E42: 43734 | F42: Marine | G42: Vinay | H42: Ahmedabad | I42: Marine | J42: Renewal | K42: 1650 | L42: 43370 | M42: Brokerage | N42: Inception | O42: 43852
A43: N | B43: 0830018899Â 01 | C43: Inactive | D43: 43160 | E43: 43524 | F43: Marine | G43: Animesh Rawat | H43: Ahmedabad | I43: Global Client Network (GNB Inward) | J43: Renewal | K43: 16335 | L43: 43160 | M43: Brokerage | N43: Inception | O43: 43852
A44: N | B44: OG-19-2202-1018-00000059 | C44: Active | D44: 43525 | E44: 43890 | F44: Marine | G44: Animesh Rawat | H44: Ahmedabad | I44: Global Client Network (GNB Inward) | J44: Renewal | K44: 18562.5 | L44: 43525 | M44: Brokerage | N44: Renewal | O44: 43852
A45: O | B45: OG-19-2001-3315-00000015 | C45: Active | D45: 43192 | E45: 43556 | F45: Liability | G45: Shivani Sharma | H45: Ahmedabad | I45: Global Client Network (GNB Inward) | J45: Renewal | K45: 0 | L45: 43314 | M45: Brokerage | N45: Inception | O45: 43852
A46: P | B46: 4005/134645920/01/000 | C46: Inactive | D46: 43280 | E46: 43644 | F46: Employee Benefits | G46: Mark | H46: Ahmedabad | I46: Employee Benefits (EB) | J46: Renewal | K46: 4330.05 | L46: 43280 | M46: Brokerage | N46: Endorsement | O46: 43852
A47: P | B47: 4005/134645920/01/000 | C47: Inactive | D47: 43280 | E47: 43644 | F47: Employee Benefits | G47: Mark | H47: Ahmedabad | I47: Employee Benefits (EB) | J47: Renewal | L47: 43286 | M47: Brokerage | N47: Endorsement | O47: 43852
A48: P | B48: 4005/134645920/02/000 | C48: Active | D48: 43645 | E48: 44010 | F48: Employee Benefits | G48: Mark | H48: Ahmedabad | I48: Employee Benefits (EB) | J48: Renewal | K48: 8604.68 | L48: 43645 | M48: Brokerage | N48: Renewal | O48: 43852
A49: P | B49: 4016/133979727/01/000 | C49: Inactive | D49: 43280 | E49: 43644 | F49: Employee Benefits | G49: Mark | H49: Ahmedabad | I49: Employee Benefits (EB) | J49: Renewal | K49: 41313.6 | L49: 43280 | M49: Brokerage | N49: Endorsement | O49: 43852
A50: P | B50: 4016/133979727/01/000 | C50: Inactive | D50: 43280 | E50: 43644 | F50: Employee Benefits | G50: Mark | H50: Ahmedabad | I50: Employee Benefits (EB) | J50: Renewal | L50: 43312 | M50: Brokerage | N50: Endorsement | O50: 43852
A51: P | B51: 4016/133979727/02/000 | C51: Active | D51: 43645 | E51: 44010 | F51: Employee Benefits | G51: Mark | H51: Ahmedabad | I51: Employee Benefits (EB) | J51: Renewal | K51: 74672.78 | L51: 43645 | M51: Brokerage | N51: Renewal | O51: 43852
A52: O | B52: 0865078861 00 | C52: Active | D52: 43103 | E52: 43467 | F52: Marine | G52: Shivani Sharma | H52: Ahmedabad | I52: Global Client Network (GNB Inward) | J52: Renewal | K52: 66622.35 | L52: 43103 | M52: Brokerage | N52: Inception | O52: 43852
A53: O | B53: 4066/130374729/01/000 | C53: Active | D53: 43191 | E53: 43555 | F53: Liability | G53: Shivani Sharma | H53: Ahmedabad | I53: Global Client Network (GNB Inward) | J53: Renewal | K53: 0 | L53: 43191 | M53: Brokerage | N53: Inception | O53: 43852
A54: q | B54: 2002/160040691/00/000 | C54: Inactive | D54: 43405 | E54: 43769 | F54: Marine | G54: Vinay | H54: Ahmedabad | I54: Marine | J54: Renewal | K54: 92812.5 | L54: 43405 | M54: Brokerage | N54: Renewal | O54: 43852
A55: q | B55: 2002/160040691/01/000 | C55: Active | D55: 43783 | E55: 44148 | F55: Marine | G55: Vinay | H55: Ahmedabad | I55: Marine | J55: Renewal | K55: 18562.5 | L55: 43783 | M55: Brokerage | N55: Renewal | O55: 43852
A56: q | B56: 2002/E/107876781/03/000 | C56: Active | D56: 43381 | E56: 43745 | F56: Marine | G56: Vinay | H56: Ahmedabad | I56: Marine | J56: Renewal | K56: 3526.88 | L56: 43746 | M56: Brokerage | N56: Renewal | O56: 43852
A57: q | B57: 2002/E/1078781/02/000 | C57: Active | D57: 43016 | E57: 43380 | F57: Marine | G57: Juli | H57: Ahmedabad | I57: Marine | J57: Renewal | K57: 34950.98 | L57: 43016 | M57: Brokerage | N57: Inception | O57: 43852
A58: q | B58: 22214272 | C58: Active | D58: 43040 | E58: 43404 | F58: Marine | G58: Juli | H58: Ahmedabad | I58: Marine | J58: Renewal | K58: 55687.5 | L58: 43040 | M58: Brokerage | N58: Inception | O58: 43852
A59: R | B59: '14220011190100000062 | C59: Active | D59: 43567 | E59: 43932 | F59: Fire | G59: Raju Kumar | H59: Ahmedabad | I59: Property / BI | J59: Renewal | K59: 5187.31 | L59: 43567 | M59: Brokerage | N59: Inception | O59: 43852
A60: o | B60: 2690000138 04 | C60: Active | D60: 43337 | E60: 43701 | F60: Fire | G60: Vinay | H60: Ahmedabad | I60: Property / BI | J60: Cross Sell | K60: 2116.48 | L60: 43337 | M60: Brokerage | N60: Inception | O60: 43852
A61: o | B61: 2690000337 03 | C61: Active | D61: 43434 | E61: 43798 | F61: Fire | G61: Vinay | H61: Ahmedabad | I61: Property / BI | J61: Renewal | K61: 810.28 | L61: 43434 | M61: Brokerage | N61: Inception | O61: 43852
A62: T | B62: 30003393 | C62: Active | D62: 43586 | E62: 43951 | F62: Miscellaneous | G62: Ketan Jain | H62: Ahmedabad | I62: Trade Credit &amp; Political Risk | J62: New | K62: 379836.08 | L62: 43586 | M62: Brokerage | N62: Inception | O62: 43852
A63: T | B63: OG-18-2202-3315-00000028 | C63: Active | D63: 43555 | E63: 43920 | F63: Liability | G63: Ketan Jain | H63: Ahmedabad | I63: Liability | J63: Cross Sell | K63: 28087.5 | L63: 43555 | M63: Brokerage | N63: Inception | O63: 43852
A64: U | B64: '23060036180200000022 | C64: Active | D64: 43466 | E64: 43830 | F64: Liability | G64: Vinay | H64: Ahmedabad | I64: Liability | J64: Renewal | K64: 137500 | L64: 43466 | M64: Brokerage | N64: Inception | O64: 43852
A65: U | B65: '2999202466609300000 | C65: Active | D65: 43377 | E65: 43741 | F65: Liability | G65: Vinay | H65: Ahmedabad | I65: Liability | J65: Cross Sell | K65: 18750 | L65: 43377 | M65: Brokerage | N65: Inception | O65: 43852
A66: U | B66: '2999203175548500000 | C66: Active | D66: 43801 | E66: 44166 | F66: Liability | G66: Vinay | H66: Ahmedabad | I66: Liability | J66: Renewal | K66: 8125 | L66: 43801 | M66: Brokerage | N66: Inception | O66: 43852
A67: V | B67: 141400/11/2018/737 | C67: Active | D67: 43160 | E67: 43524 | F67: Fire | G67: Juli | H67: Ahmedabad | I67: Small Medium Enterpries (SME) | J67: New | K67: 116487.04 | L67: 43160 | M67: Brokerage | N67: Inception | O67: 43852
A68: V | B68: 141400/11/2018/738 | C68: Active | D68: 43160 | E68: 43524 | F68: Fire | G68: Juli | H68: Ahmedabad | I68: Small Medium Enterpries (SME) | J68: New | K68: 2988.62 | L68: 43160 | M68: Brokerage | N68: Inception | O68: 43852
A69: V | B69: 141400/44/2018/101 | C69: Active | D69: 43160 | E69: 43524 | F69: Miscellaneous | G69: Juli | H69: Ahmedabad | I69: Small Medium Enterpries (SME) | J69: New | K69: 14627.5 | L69: 43160 | M69: Brokerage | N69: Inception | O69: 43852
A70: V | B70: 141400/44/2018/102 | C70: Active | D70: 43160 | E70: 43524 | F70: Miscellaneous | G70: Juli | H70: Ahmedabad | I70: Small Medium Enterpries (SME) | J70: New | K70: 2020.5 | L70: 43160 | M70: Brokerage | N70: Inception | O70: 43852
A71: V | B71: 141400/48/2018/2149 | C71: Active | D71: 43160 | E71: 43524 | F71: Miscellaneous | G71: Juli | H71: Ahmedabad | I71: Small Medium Enterpries (SME) | J71: New | K71: 625.13 | L71: 43160 | M71: Brokerage | N71: Inception | O71: 43852
A72: V | B72: 141400/48/2018/2150 | C72: Active | D72: 43160 | E72: 43524 | F72: Miscellaneous | G72: Juli | H72: Ahmedabad | I72: Small Medium Enterpries (SME) | J72: Cross Sell | K72: 417 | L72: 43160 | M72: Brokerage | N72: Inception | O72: 43852
A73: V | B73: 141400/48/2018/2237 | C73: Active | D73: 43160 | E73: 43524 | F73: Miscellaneous | G73: Juli | H73: Ahmedabad | I73: Small Medium Enterpries (SME) | J73: New | K73: 687.63 | L73: 43160 | M73: Brokerage | N73: Inception | O73: 43852
A74: V | B74: 141400/48/2018/2238 | C74: Active | D74: 43160 | E74: 43524 | F74: Liability | G74: Juli | H74: Ahmedabad | I74: Small Medium Enterpries (SME) | J74: New | K74: 374.88 | L74: 43160 | M74: Brokerage | N74: Inception | O74: 43852
... A78: AA | B78: '91000036191700000002 | C78: Active | D78: 43608 | E78: 43973 | F78: Liability | G78: Vinay | H78: Ahmedabad | I78: Liability | J78: Renewal | K78: 131250 | L78: 43608 | M78: Brokerage | N78: Inception | O78: 43852
A79: BB | B79: 302102591 | C79: Inactive | D79: 43348 | E79: 43712 | F79: Miscellaneous | G79: Animesh Rawat | H79: Ahmedabad | I79: Global Client Network (GNB Inward) | J79: Renewal | K79: 6058.38 | L79: 43348 | M79: Brokerage | N79: Inception | O79: 43852
A80: BB | B80: 668111383 | C80: Active | D80: 43025 | E80: 43389 | F80: Fire | G80: Animesh Rawat | H80: Ahmedabad | I80: Global Client Network (GNB Inward) | J80: Renewal | K80: 29608.99 | L80: 43025 | M80: Brokerage | N80: Inception | O80: 43852
A81: BB | B81: 668111383 | C81: Active | D81: 43025 | E81: 43389 | F81: Fire | G81: Animesh Rawat | H81: Ahmedabad | I81: Global Client Network (GNB Inward) | J81: Renewal | K81: 29638.4 | L81: 43025 | M81: Brokerage | N81: Inception | O81: 43852
A82: BB | B82: 668111383 | C82: Active | D82: 43025 | E82: 43389 | F82: Fire | G82: Animesh Rawat | H82: Ahmedabad | I82: Global Client Network (GNB Inward) | J82: Renewal | K82: 237107.16 | L82: 43025 | M82: Brokerage | N82: Inception | O82: 43852
A83: BB | B83: 0668111383 05 | C83: Active | D83: 43390 | E83: 43754 | F83: Miscellaneous | G83: Animesh Rawat | H83: Ahmedabad | I83: Global Client Network (GNB Inward) | J83: Renewal | K83: 295501.76 | L83: 43390 | M83: Brokerage | N83: Inception | O83: 43852
A84: BB | B84: 2250015394 | C84: Active | D84: 43713 | E84: 44078 | F84: Miscellaneous | G84: Animesh Rawat | H84: Ahmedabad | I84: Global Client Network (GNB Inward) | J84: Renewal | K84: 5612.25 | L84: 43713 | M84: Brokerage | N84: Renewal | O84: 43852
A85: BB | B85: 2309002394 | C85: Active | D85: 43101 | E85: 43465 | F85: Liability | G85: Animesh Rawat | H85: Ahmedabad | I85: Global Client Network (GNB Inward) | J85: Renewal | K85: 30875 | L85: 43101 | M85: Brokerage | N85: Inception | O85: 43852
A86: BB | B86: 3.114203e+18 | C86: Active | D86: 43703 | E86: 44068 | F86: Miscellaneous | G86: Animesh Rawat | H86: Ahmedabad | I86: Global Client Network (GNB Inward) | J86: Cross Sell | K86: 7022.25 | L86: 43703 | M86: Brokerage | N86: Inception | O86: 43852
A87: BB | B87: OG-19-2202-1018-00000053 | C87: Active | D87: 43466 | E87: 43830 | F87: Marine | G87: Animesh Rawat | H87: Ahmedabad | I87: Global Client Network (GNB Inward) | J87: Cross Sell | K87: 77787.36 | L87: 43466 | M87: Brokerage | N87: Inception | O87: 43852
A88: BB | B88: OG-19-2202-3383-00000008 | C88: Active | D88: 43466 | E88: 43830 | F88: Liability | G88: Animesh Rawat | H88: Ahmedabad | I88: Global Client Network (GNB Inward) | J88: Cross Sell | K88: 30048.08 | L88: 43466 | M88: Brokerage | N88: Inception | O88: 43852
A89: BB | B89: PROHLN000242106 | C89: Active | D89: 43724 | E89: 44089 | F89: Employee Benefits | G89: Animesh Rawat | H89: Ahmedabad | I89: Global Client Network (GNB Inward) | J89: Cross Sell | K89: 7690.95 | L89: 43724 | M89: Brokerage | N89: Inception | O89: 43852
A90: BB | B90: 1.2030046e+19 | C90: Inactive | D90: 43322 | E90: 43686 | F90: Miscellaneous | G90: Shivani Sharma | H90: Ahmedabad | I90: Global Client Network (GNB Inward) | J90: Renewal | K90: 86400 | L90: 43322 | M90: Brokerage | N90: Inception | O90: 43852
A91: BB | B91: 1.2030046e+19 | C91: Inactive | D91: 43322 | E91: 43686 | F91: Miscellaneous | G91: Shivani Sharma | H91: Ahmedabad | I91: Global Client Network (GNB Inward) | J91: Renewal | K91: 345705 | L91: 43322 | M91: Brokerage | N91: Inception | O91: 43852
A92: BB | B92: 1.2030046e+19 | C92: Active | D92: 43687 | E92: 44052 | F92: Miscellaneous | G92: Animesh Rawat | H92: Ahmedabad | I92: Global Client Network (GNB Inward) | J92: Renewal | K92: 77400 | L92: 43687 | M92: Brokerage | N92: Renewal | O92: 43852
A93: BB | B93: 1.2030046e+19 | C93: Active | D93: 43687 | E93: 44052 | F93: Miscellaneous | G93: Animesh Rawat | H93: Ahmedabad | I93: Global Client Network (GNB Inward) | J93: Renewal | K93: 302811.08 | L93: 43687 | M93: Brokerage | N93: Renewal | O93: 43852
A94: BB | B94: P0319200002/9999/100065 | C94: Active | D94: 43282 | E94: 43646 | F94: Liability | G94: Shivani Sharma | H94: Ahmedabad | I94: Global Client Network (GNB Inward) | J94: Renewal | K94: 1183.38 | L94: 43282 | M94: Brokerage | N94: Inception | O94: 43852
A95: S | B95: 2018-F0541357-FRE | C95: Active | D95: 43359 | E95: 43723 | F95: Fire | G95: Vinay | H95: Ahmedabad | I95: Property / BI | J95: Renewal | K95: 33977.82 | L95: 43359 | M95: Brokerage | N95: Inception | O95: 43852
A96: BB | B96: '11120044170300000009 | C96: Active | D96: 43066 | E96: 44161 | F96: Engineering | G96: Raju Kumar | H96: Ahmedabad | I96: Construction, Power & Infrastructure | J96: Cross Sell | K96: 25303.02 | L96: 43247 | M96: Brokerage | N96: Inception | O96: 43852
A97: BB | B97: '11120044170300000009 | C97: Active | D97: 43066 | E97: 44161 | F97: Engineering | G97: Raju Kumar | H97: Ahmedabad | I97: Construction, Power & Infrastructure | J97: Cross Sell | K97: 25302.96 | L97: 43612 | M97: Brokerage | N97: Inception | O97: 43852
A98: BB | B98: '11120044170300000009 | C98: Active | D98: 43066 | E98: 44161 | F98: Engineering | G98: Raju Kumar | H98: Ahmedabad | I98: Construction, Power & Infrastructure | J98: Cross Sell | K98: 25302.96 | L98: 43704 | M98: Brokerage | N98: Inception | O98: 43852
A99: BB | B99: '11120044170300000009 | C99: Active | D99: 43066 | E99: 44161 | F99: Engineering | G99: Raju Kumar | H99: Ahmedabad | I99: Construction, Power & Infrastructure | J99: Cross Sell | K99: 25302.96 | L99: 43796 | M99: Brokerage | N99: Inception | O99: 43852
A100: BB | B100: '11120044170300000009 | C100: Active | D100: 43066 | E100: 44161 | F100: Engineering | G100: Raju Kumar | H100: Ahmedabad | I100: Construction, Power & Infrastructure | J100: Cross Sell | K100: 25302.96 | L100: 43888 | M100: Brokerage | N100: Inception | O100: 43852
A101: BB | B101: '11120044170300000009 | C101: Active | D101: 43066 | E101: 44161 | F101: Engineering | G101: Raju Kumar | H101: Ahmedabad | I101: Construction, Power & Infrastructure | J101: Cross Sell | K101: 25302.96 | L101: 43978 | M101: Brokerage | N101: Inception | O101: 43852
A102: BB | B102: '11120044170300000009 | C102: Active | D102: 43066 | E102: 44161 | F102: Engineering | G102: Raju Kumar | H102: Ahmedabad | I102: Construction, Power & Infrastructure | J102: Cross Sell | K102: 25302.96 | L102: 43339 | M102: Brokerage | N102: Inception | O102: 43852
A103: BB | B103: '11120044170300000009 | C103: Active | D103: 43066 | E103: 44161 | F103: Engineering | G103: Raju Kumar | H103: Ahmedabad | I103: Construction, Power & Infrastructure | J103: Cross Sell | K103: 25302.96 | L103: 43431 | M103: Brokerage | N103: Inception | O103: 43852
...

Sheet Cross sell
A1: income_class | B1: Cross Sell
A2: income_class | B2: Cross Sell
A4: Values
A5: Target | B5: 7290000
A6: Achivement | B6: 13041253
A7: Invoice | B7: 2853842

Sheet New
A1: income_class | B1: New
A2: income_class | B2: New
A4: Values
A5: Target | B5: 4100000
A6: Achivement | B6: 3531629.3
A7: Invoice | B7: 569815

Sheet Renewal
A1: income_class | B1: Renewal
A2: income_class | B2: Renewal
A4: Values
A5: Target | B5: 9520000
A6: Achivement | B6: 18507271
A7: Invoice | B7: 8244310

Sheet % Achivement
A2: Invoice
A3: Row Labels | B3: Sum of Amount | E3: Target
A4: Cross Sell | B4: 2853842 | E4: Sum of New Budget | F4: Sum of Cross sell bugdet | G4: Sum of Renewal Budget
A5: New | B5: 569815 | E5: 4100000 | F5: 7290000 | G5: 9520000
A6: Renewal | B6: 8244310
A7: Grand Total | B7: 11667967
E9: Cross Sell Placd Ach % | F9: Cross Sell Invoice Ach %
E10: =GETPIVOTDATA("[Measures].[Sum of Amount 2]",$A$18,"[Placed_achivement].[income_class]","[Placed_achivement].[income_class].&[Cross Sell]")/GETPIVOTDATA("Sum of Cross sell bugdet",$E$4) -> 1.7889236 | F10: =GETPIVOTDATA("Amount",$A$3,"income_class","Cross Sell")/GETPIVOTDATA("Sum of Cross sell bugdet",$E$4) -> 0.39147353
E13: New Placd Ach % | F13: New Invoice Ach %
E14: =GETPIVOTDATA("[Measures].[Sum of Amount 2]",$A$18,"[Placed_achivement].[income_class]","[Placed_achivement].[income_class].&[New]")/GETPIVOTDATA("Sum of New Budget",$E$4) -> 0.861373 | F14: =GETPIVOTDATA("Amount",$A$3,"income_class","New")/GETPIVOTDATA("Sum of New Budget",$E$4) -> 0.13897927
A17: Achivement | E17: Renewal Placd Ach % | F17: Renewal Invoice Ach %
A18: Row Labels | B18: Sum of Amount | E18: =GETPIVOTDATA("[Measures].[Sum of Amount 2]",$A$18,"[Placed_achivement].[income_class]","[Placed_achivement].[income_class].&[Renewal]")/GETPIVOTDATA("Sum of Renewal Budget",$E$4) -> 1.944041 | F18: =GETPIVOTDATA("Amount",$A$3,"income_class","Renewal")/GETPIVOTDATA("Sum of Renewal Budget",$E$4) -> 0.86599895
A19: Cross Sell | B19: 13041253
A20: New | B20: 3531629.3
A21: Renewal | B21: 18507271
A22: Grand Total | B22: 35080153

Sheet % achievement
A2: Formula | B2: Cross sell
A3: Achieved/Target | B3: Cross sell Plcd Achvmnt% | C3: ='[1]KPI 3.1'!C69/'[1]KPI 3.1'!C68 -> 0.58705063
A4: Invoice/Target | B4: Cross sell Inv Achvmnt% | C4: ='[1]KPI 3.1'!C70/'[1]KPI 3.1'!C68 -> 0.14210159
B6: New
A7: Achieved/Target | B7: New Plcd Achvmnt% | C7: ='[1]KPI 3.1'!C75/'[1]KPI 3.1'!C74 -> 0.16569861
A8: Invoice/Target | B8: New sell Inv Achvmnt% | C8: ='[1]KPI 3.1'!C76/'[1]KPI 3.1'!C74 -> 0.028963149
B10: Renewal
A11: Achieved/Target | B11: Renewal Plcd Achvmnt% | C11: ='[1]KPI 3.1'!C80/'[1]KPI 3.1'!C81 -> 0.66834911
A12: Invoice/Target | B12: Renewal Inv Achvmnt% | C12: ='[1]KPI 3.1'!C82/'[1]KPI 3.1'!C81 -> 0.44726631

Sheet KPI 1
A3: Count of invoice_number | B3: Column Labels
A4: Row Labels | B4: (blank) | C4: Cross Sell | D4: New | E4: Renewal | F4: Grand Total
A5: Neel Jain | D5: 1 | F5: 1
A6: Gautam Murkunde | B6: 1 | E6: 3 | F6: 4
A7: Nishant Sharma | C7: 10 | F7: 10
A8: Shobhit Agarwal | B8: 4 | C8: 2 | D8: 8 | F8: 14
A9: Vidit Shah | C9: 12 | E9: 15 | F9: 27
A10: Shloka Shelat | C10: 20 | D10: 7 | E10: 3 | F10: 30
A11: Ankita Shah | B11: 18 | E11: 18 | F11: 36
A12: Divya Dhingra | B12: 5 | C12: 19 | E12: 58 | F12: 82
A13: Grand Total | B13: 28 | C13: 63 | D13: 16 | E13: 97 | F13: 204

Sheet KPI 2
A3: Row Labels | B3: Count of Account Executive
A4: 2019 | B4: 3 | F4: Yearly Meeting Count
A5: 2020 | B5: 31 | F5: =A4 -> 2019 | G5: =A5 -> 2020
A6: Grand Total | B6: 34 | F6: =GETPIVOTDATA("[Measures].[Count of Account Executive]",$A$3,"[meeting_list_202001231041].[meeting_date (Year)]","[meeting_list_202001231041].[meeting_date (Year)].&[2019]") -> 3 | G6: =GETPIVOTDATA("[Measures].[Count of Account Executive]",$A$3,"[meeting_list_202001231041].[meeting_date (Year)]","[meeting_list_202001231041].[meeting_date (Year)].&[2020]") -> 31

Sheet KPI 4
A3: Row Labels | B3: Sum of revenue_amount
A4: Propose Solution | B4: 60000
A5: Negotiate | B5: 899000
A6: Qualify Opportunity | B6: 5919500
A7: Grand Total | B7: 6878500
B10: Qualify Opportunity | C10: 5919500
B11: Negotiate | C11: 899000
B12: Propose Solution | C12: 60000

Sheet KPI 5
A3: Row Labels | B3: Count of meeting_date
A4: Raju Kumar | B4: 2
A5: Mark | B5: 2
A6: Manish Sharma | B6: 3
A7: Juli | B7: 3
A8: Animesh Rawat | B8: 4
A9: Ketan Jain | B9: 4
A10: Shivani Sharma | B10: 4
A11: Vinay | B11: 5
A12: Abhinav Shivam | B12: 7
A13: Grand Total | B13: 34

Sheet KPI3
A3: Cross sell | B3: Refer sheet | H3: New | I3: Refer sheet | O3: Renewal | P3: Refer sheet
A4: Target | B4: Budget | C4: 20083111 | H4: Target | I4: Budget | J4: 19673793 | O4: Target | P4: Budget | Q4: 12319455
A5: Achievement | B5: Brokerage+Fees | C5: 11789803 | H5: Achievement | I5: Brokerage+Fees | J5: 3259920.1 | O5: Achievement | P5: Brokerage+Fees | Q5: 18432665
A6: Invoice | B6: invoice | C6: 2853842 | H6: Invoice | I6: invoice | J6: 569815 | O6: Invoice | P6: invoice | Q6: 8244310
A8: Cross sell | B8: Target | C8: Row Labels | D8: Sum of cross_sell_budget | H8: Cross sell | I8: Target | J8: Row Labels | K8: Sum of new_budget | O8: Cross sell | P8: Target | Q8: Row Labels | R8: Sum of renewal_budget
C9: Abhinav Shivam | D9: 129000 | J9: Abhinav Shivam | K9: 129902 | Q9: Abhinav Shivam | R9: 1289000
C10: Animesh Rawat | D10: 12365300 | J10: Animesh Rawat | K10: 1278023 | Q10: Animesh Rawat | R10: 12900
C11: Ankita Shah | D11: 0 | J11: Ankita Shah | K11: 0 | Q11: Ankita Shah | R11: 0
C12: Divya Dhingra | D12: 0 | J12: Divya Dhingra | K12: 0 | Q12: Divya Dhingra | R12: 0
C13: Gautam Murkunde | D13: 0 | J13: Gautam Murkunde | K13: 0 | Q13: Gautam Murkunde | R13: 0
C14: Gilbert | D14: 500000 | J14: Gilbert | K14: 1000000 | Q14: Gilbert | R14: 1010000
C15: Juli | D15: 3500000 | J15: Juli | K15: 1250000 | Q15: Juli | R15: 750000
C16: Ketan Jain | D16: 1250000 | J16: Ketan Jain | K16: 500000 | Q16: Ketan Jain | R16: 500000
C17: Kumar Jha | D17: 170034 | J17: Kumar Jha | K17: 1345000 | Q17: Kumar Jha | R17: 1298673
C18: Manish Sharma | D18: 750000 | J18: Manish Sharma | K18: 1350000 | Q18: Manish Sharma | R18: 750000
C19: Mark | D19: 128777 | J19: Mark | K19: 19888 | Q19: Mark | R19: 198882
C20: Neel Jain | D20: 0 | J20: Neel Jain | K20: 0 | Q20: Neel Jain | R20: 0
... C31: Target | D31: 20083111 | J31: Target | K31: 19673793 | Q31: Target | R31: 12319455
A33: Cross sell | B33: Achievement | C33: Row Labels | D33: Cross Sell(Brokerage) | E33: Row Labels | F33: Cross Sell(Fees) | H33: New | I33: Achievement | J33: New(Brokerage) | L33: New(Fees) | O33: New | P33: Achievement | Q33: Row Labels | R33: Renewal | S33: Row Labels | T33: Renewal
B34: (Brokerage+Fees) | C34: Abhinav Shivam | D34: 206294.29 | E34: Nishant Sharma | F34: 396480 | J34: Abhinav Shivam | K34: 567352.74 | L34: Abhinav Shivam | M34: 100000 | Q34: Abhinav Shivam | R34: 109812.12 | S34: Vinay | T34: 18051
C35: Animesh Rawat | D35: 543713.53 | J35: Animesh Rawat | K35: 55107.13 | Q35: Animesh Rawat | R35: 6412986.2
C36: Gilbert | J36: Juli | K36: 150230.05 | Q36: Gilbert | R36: 386738.25
C37: Juli | D37: 417 | J37: Ketan Jain | K37: 743804.31 | Q37: Juli | R37: 149485.39
C38: Ketan Jain | D38: 28087.5 | J38: Raju Kumar | K38: 100000 | Q38: Ketan Jain | R38: 369095.49
C39: Kumar Jha | J39: Vididt Saha | K39: 319390.82 | Q39: Kumar Jha | R39: 130049.5
C40: Manish Sharma | D40: 36357.09 | J40: Vinay | K40: 1224035 | Q40: Manish Sharma | R40: 29928.34
C41: Mark | D41: 63872.4 | J41: Grand Total | K41: 3159920.1 | L41: Grand Total | M41: 100000 | Q41: Mark | R41: 5001503.1
C42: Raju Kumar | D42: 821261.22 | Q42: Raju Kumar | R42: 452577.19
C43: Shivani Sharma | D43: 22047 | K43: Achievement | L43: =SUM(K41,M41) -> 3259920.1 | Q43: Shivani Sharma | R43: 888648.86
C44: Vididt Saha | D44: 1103800.2 | Q44: Vididt Saha | R44: 144957.51
C45: Vinay | D45: 8567472.7 | Q45: Vinay | R45: 4338831.7
C46: Grand Total | D46: 11393323 | E46: Grand Total | F46: 396480 | Q46: Grand Total | R46: 18414614 | S46: Grand Total | T46: 18051
D48: Achievement | E48: =SUM(D46,F46) -> 11789803 | Q48: Achievement | R48: =SUM(R46,T46) -> 18432665
A50: Cross sell | B50: Invoice | C50: Row Labels | D50: Cross Sell | H50: Renewal | I50: Invoice | J50: Row Labels | K50: New | O50: Renewal | P50: Invoice | Q50: Row Labels | R50: Renewal
C51: Abhinav Shivam | D51: 1012346 | J51: Neel Jain | K51: 84746 | Q51: Ankita Shah | R51: 1981422
C52: Animesh Rawat | D52: 443901 | J52: Shloka Shelat | K52: 224533 | Q52: Divya Dhingra | R52: 4351921
C53: Ankita Shah | J53: Shobhit Agarwal | K53: 260536 | Q53: Gautam Murkunde | R53: 305707
C54: Divya Dhingra | J54: Grand Total | K54: 569815 | Q54: Shloka Shelat | R54: 56098
C55: Gautam Murkunde | Q55: Vidit Shah | R55: 1549162
C56: Mark | D56: 90530 | J56: Invoice | K56: 569815 | Q56: Grand Total | R56: 8244310
C57: Neel Jain
C58: Shloka Shelat | Q58: Invoice | R58: 8244310
C59: Shobhit Agarwal
C60: Vidit Shah | D60: 895232
C61: Vinay | D61: 411833
C62: Grand Total | D62: 2853842
C64: Invoice | D64: 11789803
B66: KPI -1.1 | C66: Cross Cell total sum
B67: Cross Cell | C67: Total Sum
B68: Target | C68: =$C$4 -> 20083111
B69: Achieved | C69: =$C$5 -> 11789803
B70: Invoice | C70: =$C$6 -> 2853842
B72: KPI -1.1 | C72: New Cell total sum
B73: New | C73: Total Sum
B74: Target | C74: =J4 -> 19673793
B75: Achieved | C75: =J5 -> 3259920.1
B76: Invoice | C76: =J6 -> 569815
B78: KPI -1.1 | C78: Renewal Cell total sum
B79: Renewal | C79: Total Sum
B80: Achieved | C80: =Q4 -> 12319455
B81: Target | C81: =Q5 -> 18432665
B82: Invoice | C82: =Q6 -> 8244310

Sheet KPI 6
H1: stage | I1: (Multiple Items)
A3: Row Labels | B3: Sum of revenue_amount | H3: Row Labels | I3: Sum of revenue_amount | O3: Total Opportunity
A4: Fire | B4: 500000 | H4: BE-Mega policy | I4: 300000 | O4: 49
A5: EL-Group Mediclaim | B5: 400000 | H5: CVP GMC | I5: 350000
A6: DB -Mega Policy | B6: 400000 | H6: DB -Mega Policy | I6: 400000
A7: CVP GMC | B7: 350000 | H7: DB -Terrorism Policy | I7: 300000
A8: Grand Total | B8: 1650000 | H8: DS- Employees GMC | I8: 300000
H9: EL-Group Mediclaim | I9: 400000
H10: FM-Group Mediclaim | I10: 300000
H11: Grand Total | I11: 2350000
M20: stage | N20: (Multiple Items)
K22: Total opportunity | M22: open opportunity
K23: 49 | M23: 44

Sheet KPI 7
A3: Row Labels | B3: Count of product_group
A4: Terrorism | B4: 1
A5: Miscellaneous | B5: 2
A6: Liability | B6: 5
A7: Engineering | B7: 6
A8: Marine | B8: 7
A9: Fire | B9: 13
A10: Employee Benefits | B10: 15
A11: Grand Total | B11: 49

Sheet Dashboard 
B18: Cross Sell Placd Ach % | D18: Cross Sell Invoice Ach % | F18: New Placd Ach % | H18: New Invoice Ach % | J18: Renewal Placd Ach % | L18: Renewal Invoice Ach %
B19: ='% Achivement'!E10 -> 1.7889236 | D19: ='% Achivement'!F10 -> 0.39147353 | F19: ='% Achivement'!E14 -> 0.861373 | H19: ='% Achivement'!F14 -> 0.13897927 | J19: ='% Achivement'!E18 -> 1.944041 | L19: ='% Achivement'!F18 -> 0.86599895
K21: Total Opprtunities | M21: Total Open Opportunities
K22: =GETPIVOTDATA("[Measures].[Count of opportunity_name]",'KPI 6'!$O$3) -> 49 | M22: =GETPIVOTDATA("opportunity_name",'KPI 6'!$M$22) -> 44
B23: 2019 | D23: 2020
B24: ='KPI 2'!F6 -> 3 | D24: ='KPI 2'!G6 -> 31
